Workbook

Sheet README
B2: Multi-Store Sales Consolidation Pipeline
B4: Business Problem
B5: 6+ stores each send a weekly sales export from their own point-of-sale system. Each system labels the store slightly differently, formats numbers slightly differently, and occasionally double-submits a row. Combining and standardizing these by hand every week doesn't scale — and errors compound silently if it's not done consistently.
B7: Excel Skills Demonstrated
B8: • Data cleaning: TRIM/VALUE to fix inconsistent whitespace and text-formatted numbers
B9: • A star-schema style model: one fact table (Sales) joined to three dimension tables (Store, Product, Calendar) via INDEX/MATCH — the relational structure Power Pivot's Data Model is built on
B10: • Duplicate detection and removal (COUNTIFS-based flagging)
B11: • Store-name standardization via a mapping/lookup table
B12: • SUMIFS-based measures shown side by side with their DAX equivalents (SUMX, CALCULATE)
B13: • A documented Power Query step list and a one-click VBA refresh macro, for use in a live Excel copy with real file connections
B15: A Note on Power Query, Power Pivot, and VBA
B16: Power Query connections, a Power Pivot Data Model, and VBA macros are all live, interactive Excel features stored as complex binary/XML structures that a portable, from-scratch .xlsx file can't reliably carry — they need to be built inside Excel itself, pointed at real files and refreshed there. So this workbook does the honest thing: it builds the exact same fact + dimension table structure and cleaning logic using plain formulas (fully portable, recalculates anywhere), and separately documents — on the Power Query Steps and Refresh Macro sheets — the literal steps and VBA code you'd use to automate this for real in a live Excel workbook connected to a folder of CSVs.
... B30: Source: synthetic multi-store export data generated for this project (see gen_raw_exports.py), with store-label inconsistencies and duplicate rows intentionally injected. Product master shared with the other projects in this repo for portfolio continuity.

Sheet Dashboard
B2: Multi-Store Sales Consolidation Dashboard
B3: 6 Stores | 8 Weekly Export Batches | 1,241 Raw Rows In
B5: Total Revenue (Clean) | D5: Clean Transactions | F5: Duplicate Rows Removed | H5: Stores Consolidated
B6: ='Consolidated Master'!I1244 -> 188741 | D6: ='Consolidated Master'!I1246 -> 1194 | F6: ='Consolidated Master'!I1245 -> 47 | H6: ='Measures (DAX vs Excel)'!D7 -> 6
B9: Every number above traces back to Consolidated Master, which stays in sync automatically if Raw Store Exports, Store Mapping, or Product Master change.
B11: Store | C11: Revenue | F11: Category | G11: Revenue
B12: Airport Plaza | C12: =SUMIFS('Consolidated Master'!I2:I1242,'Consolidated Master'!C2:C1242,B12,'Consolidated Master'!J2:J1242,"") -> 29211 | F12: Accessories | G12: =SUMIFS('Consolidated Master'!I2:I1242,'Consolidated Master'!F2:F1242,F12,'Consolidated Master'!J2:J1242,"") -> 20422
B13: Downtown | C13: =SUMIFS('Consolidated Master'!I2:I1242,'Consolidated Master'!C2:C1242,B13,'Consolidated Master'!J2:J1242,"") -> 32760 | F13: Apparel | G13: =SUMIFS('Consolidated Master'!I2:I1242,'Consolidated Master'!F2:F1242,F13,'Consolidated Master'!J2:J1242,"") -> 39758
B14: Eastgate | C14: =SUMIFS('Consolidated Master'!I2:I1242,'Consolidated Master'!C2:C1242,B14,'Consolidated Master'!J2:J1242,"") -> 27943 | F14: Electronics | G14: =SUMIFS('Consolidated Master'!I2:I1242,'Consolidated Master'!F2:F1242,F14,'Consolidated Master'!J2:J1242,"") -> 49098
B15: Northpark | C15: =SUMIFS('Consolidated Master'!I2:I1242,'Consolidated Master'!C2:C1242,B15,'Consolidated Master'!J2:J1242,"") -> 32399 | F15: Footwear | G15: =SUMIFS('Consolidated Master'!I2:I1242,'Consolidated Master'!F2:F1242,F15,'Consolidated Master'!J2:J1242,"") -> 57772
B16: Riverside | C16: =SUMIFS('Consolidated Master'!I2:I1242,'Consolidated Master'!C2:C1242,B16,'Consolidated Master'!J2:J1242,"") -> 32503 | F16: Home Goods | G16: =SUMIFS('Consolidated Master'!I2:I1242,'Consolidated Master'!F2:F1242,F16,'Consolidated Master'!J2:J1242,"") -> 21691
B17: Westside Mall | C17: =SUMIFS('Consolidated Master'!I2:I1242,'Consolidated Master'!C2:C1242,B17,'Consolidated Master'!J2:J1242,"") -> 33925

Sheet Consolidated Master
A1: Transaction ID | B1: Date | C1: Store | D1: SKU | E1: Product | F1: Category | G1: Clean Units | H1: Unit Price | I1: Revenue | J1: Is Duplicate?
A2: ='Raw Store Exports'!A2 -> TXN01054 | B2: ='Raw Store Exports'!C2 -> 46079 | C2: =INDEX('Store Mapping'!$C$2:$C$19,MATCH(TRIM('Raw Store Exports'!B2),'Store Mapping'!$A$2:$A$19,0)) -> Downtown | D2: ='Raw Store Exports'!D2 -> ELE-404 | E2: =INDEX('Product Master'!$B$2:$B$21,MATCH(D2,'Product Master'!$A$2:$A$21,0)) -> Phone Charging Cable | F2: =INDEX('Product Master'!$C$2:$C$21,MATCH(D2,'Product Master'!$A$2:$A$21,0)) -> Electronics | G2: =VALUE(TRIM('Raw Store Exports'!E2&"")) -> 1 | H2: =INDEX('Product Master'!$D$2:$D$21,MATCH(D2,'Product Master'!$A$2:$A$21,0)) -> 12 | I2: =G2*H2 -> 12 | J2: =IF(COUNTIF($A$2:A2,A2)>1,"Duplicate","")
A3: ='Raw Store Exports'!A3 -> TXN00098 | B3: ='Raw Store Exports'!C3 -> 46032 | C3: =INDEX('Store Mapping'!$C$2:$C$19,MATCH(TRIM('Raw Store Exports'!B3),'Store Mapping'!$A$2:$A$19,0)) -> Riverside | D3: ='Raw Store Exports'!D3 -> ACC-304 | E3: =INDEX('Product Master'!$B$2:$B$21,MATCH(D3,'Product Master'!$A$2:$A$21,0)) -> Wool Beanie | F3: =INDEX('Product Master'!$C$2:$C$21,MATCH(D3,'Product Master'!$A$2:$A$21,0)) -> Accessories | G3: =VALUE(TRIM('Raw Store Exports'!E3&"")) -> 6 | H3: =INDEX('Product Master'!$D$2:$D$21,MATCH(D3,'Product Master'!$A$2:$A$21,0)) -> 16 | I3: =G3*H3 -> 96 | J3: =IF(COUNTIF($A$2:A3,A3)>1,"Duplicate","")
A4: ='Raw Store Exports'!A4 -> TXN00570 | B4: ='Raw Store Exports'!C4 -> 46048 | C4: =INDEX('Store Mapping'!$C$2:$C$19,MATCH(TRIM('Raw Store Exports'!B4),'Store Mapping'!$A$2:$A$19,0)) -> Airport Plaza | D4: ='Raw Store Exports'!D4 -> HOM-504 | E4: =INDEX('Product Master'!$B$2:$B$21,MATCH(D4,'Product Master'!$A$2:$A$21,0)) -> Bamboo Cutting Board | F4: =INDEX('Product Master'!$C$2:$C$21,MATCH(D4,'Product Master'!$A$2:$A$21,0)) -> Home Goods | G4: =VALUE(TRIM('Raw Store Exports'!E4&"")) -> 4 | H4: =INDEX('Product Master'!$D$2:$D$21,MATCH(D4,'Product Master'!$A$2:$A$21,0)) -> 27 | I4: =G4*H4 -> 108 | J4: =IF(COUNTIF($A$2:A4,A4)>1,"Duplicate","")
A5: ='Raw Store Exports'!A5 -> TXN00369 | B5: ='Raw Store Exports'!C5 -> 46043 | C5: =INDEX('Store Mapping'!$C$2:$C$19,MATCH(TRIM('Raw Store Exports'!B5),'Store Mapping'!$A$2:$A$19,0)) -> Northpark | D5: ='Raw Store Exports'!D5 -> HOM-501 | E5: =INDEX('Product Master'!$B$2:$B$21,MATCH(D5,'Product Master'!$A$2:$A$21,0)) -> Ceramic Coffee Mug Set | F5: =INDEX('Product Master'!$C$2:$C$21,MATCH(D5,'Product Master'!$A$2:$A$21,0)) -> Home Goods | G5: =VALUE(TRIM('Raw Store Exports'!E5&"")) -> 2 | H5: =INDEX('Product Master'!$D$2:$D$21,MATCH(D5,'Product Master'!$A$2:$A$21,0)) -> 22 | I5: =G5*H5 -> 44 | J5: =IF(COUNTIF($A$2:A5,A5)>1,"Duplicate","")
A6: ='Raw Store Exports'!A6 -> TXN00974 | B6: ='Raw Store Exports'!C6 -> 46075 | C6: =INDEX('Store Mapping'!$C$2:$C$19,MATCH(TRIM('Raw Store Exports'!B6),'Store Mapping'!$A$2:$A$19,0)) -> Eastgate | D6: ='Raw Store Exports'!D6 -> ELE-401 | E6: =INDEX('Product Master'!$B$2:$B$21,MATCH(D6,'Product Master'!$A$2:$A$21,0)) -> Wireless Earbuds | F6: =INDEX('Product Master'!$C$2:$C$21,MATCH(D6,'Product Master'!$A$2:$A$21,0)) -> Electronics | G6: =VALUE(TRIM('Raw Store Exports'!E6&"")) -> 6 | H6: =INDEX('Product Master'!$D$2:$D$21,MATCH(D6,'Product Master'!$A$2:$A$21,0)) -> 79 | I6: =G6*H6 -> 474 | J6: =IF(COUNTIF($A$2:A6,A6)>1,"Duplicate","")
A7: ='Raw Store Exports'!A7 -> TXN00623 | B7: ='Raw Store Exports'!C7 -> 46055 | C7: =INDEX('Store Mapping'!$C$2:$C$19,MATCH(TRIM('Raw Store Exports'!B7),'Store Mapping'!$A$2:$A$19,0)) -> Westside Mall | D7: ='Raw Store Exports'!D7 -> ACC-303 | E7: =INDEX('Product Master'!$B$2:$B$21,MATCH(D7,'Product Master'!$A$2:$A$21,0)) -> Canvas Tote Bag | F7: =INDEX('Product Master'!$C$2:$C$21,MATCH(D7,'Product Master'!$A$2:$A$21,0)) -> Accessories | G7: =VALUE(TRIM('Raw Store Exports'!E7&"")) -> 1 | H7: =INDEX('Product Master'!$D$2:$D$21,MATCH(D7,'Product Master'!$A$2:$A$21,0)) -> 24 | I7: =G7*H7 -> 24 | J7: =IF(COUNTIF($A$2:A7,A7)>1,"Duplicate","")
A8: ='Raw Store Exports'!A8 -> TXN00930 | B8: ='Raw Store Exports'!C8 -> 46073 | C8: =INDEX('Store Mapping'!$C$2:$C$19,MATCH(TRIM('Raw Store Exports'!B8),'Store Mapping'!$A$2:$A$19,0)) -> Westside Mall | D8: ='Raw Store Exports'!D8 -> ELE-401 | E8: =INDEX('Product Master'!$B$2:$B$21,MATCH(D8,'Product Master'!$A$2:$A$21,0)) -> Wireless Earbuds | F8: =INDEX('Product Master'!$C$2:$C$21,MATCH(D8,'Product Master'!$A$2:$A$21,0)) -> Electronics | G8: =VALUE(TRIM('Raw Store Exports'!E8&"")) -> 2 | H8: =INDEX('Product Master'!$D$2:$D$21,MATCH(D8,'Product Master'!$A$2:$A$21,0)) -> 79 | I8: =G8*H8 -> 158 | J8: =IF(COUNTIF($A$2:A8,A8)>1,"Duplicate","")
A9: ='Raw Store Exports'!A9 -> TXN00449 | B9: ='Raw Store Exports'!C9 -> 46049 | C9: =INDEX('Store Mapping'!$C$2:$C$19,MATCH(TRIM('Raw Store Exports'!B9),'Store Mapping'!$A$2:$A$19,0)) -> Downtown | D9: ='Raw Store Exports'!D9 -> ELE-402 | E9: =INDEX('Product Master'!$B$2:$B$21,MATCH(D9,'Product Master'!$A$2:$A$21,0)) -> Bluetooth Speaker | F9: =INDEX('Product Master'!$C$2:$C$21,MATCH(D9,'Product Master'!$A$2:$A$21,0)) -> Electronics | G9: =VALUE(TRIM('Raw Store Exports'!E9&"")) -> 1 | H9: =INDEX('Product Master'!$D$2:$D$21,MATCH(D9,'Product Master'!$A$2:$A$21,0)) -> 59 | I9: =G9*H9 -> 59 | J9: =IF(COUNTIF($A$2:A9,A9)>1,"Duplicate","")
A10: ='Raw Store Exports'!A10 -> TXN01023 | B10: ='Raw Store Exports'!C10 -> 46069 | C10: =INDEX('Store Mapping'!$C$2:$C$19,MATCH(TRIM('Raw Store Exports'!B10),'Store Mapping'!$A$2:$A$19,0)) -> Riverside | D10: ='Raw Store Exports'!D10 -> APP-101 | E10: =INDEX('Product Master'!$B$2:$B$21,MATCH(D10,'Product Master'!$A$2:$A$21,0)) -> Classic Denim Jacket | F10: =INDEX('Product Master'!$C$2:$C$21,MATCH(D10,'Product Master'!$A$2:$A$21,0)) -> Apparel | G10: =VALUE(TRIM('Raw Store Exports'!E10&"")) -> 2 | H10: =INDEX('Product Master'!$D$2:$D$21,MATCH(D10,'Product Master'!$A$2:$A$21,0)) -> 68 | I10: =G10*H10 -> 136 | J10: =IF(COUNTIF($A$2:A10,A10)>1,"Duplicate","")
A11: ='Raw Store Exports'!A11 -> TXN00639 | B11: ='Raw Store Exports'!C11 -> 46056 | C11: =INDEX('Store Mapping'!$C$2:$C$19,MATCH(TRIM('Raw Store Exports'!B11),'Store Mapping'!$A$2:$A$19,0)) -> Westside Mall | D11: ='Raw Store Exports'!D11 -> HOM-502 | E11: =INDEX('Product Master'!$B$2:$B$21,MATCH(D11,'Product Master'!$A$2:$A$21,0)) -> Scented Candle | F11: =INDEX('Product Master'!$C$2:$C$21,MATCH(D11,'Product Master'!$A$2:$A$21,0)) -> Home Goods | G11: =VALUE(TRIM('Raw Store Exports'!E11&"")) -> 3 | H11: =INDEX('Product Master'!$D$2:$D$21,MATCH(D11,'Product Master'!$A$2:$A$21,0)) -> 15 | I11: =G11*H11 -> 45 | J11: =IF(COUNTIF($A$2:A11,A11)>1,"Duplicate","")
A12: ='Raw Store Exports'!A12 -> TXN00316 | B12: ='Raw Store Exports'!C12 -> 46043 | C12: =INDEX('Store Mapping'!$C$2:$C$19,MATCH(TRIM('Raw Store Exports'!B12),'Store Mapping'!$A$2:$A$19,0)) -> Westside Mall | D12: ='Raw Store Exports'!D12 -> APP-101 | E12: =INDEX('Product Master'!$B$2:$B$21,MATCH(D12,'Product Master'!$A$2:$A$21,0)) -> Classic Denim Jacket | F12: =INDEX('Product Master'!$C$2:$C$21,MATCH(D12,'Product Master'!$A$2:$A$21,0)) -> Apparel | G12: =VALUE(TRIM('Raw Store Exports'!E12&"")) -> 1 | H12: =INDEX('Product Master'!$D$2:$D$21,MATCH(D12,'Product Master'!$A$2:$A$21,0)) -> 68 | I12: =G12*H12 -> 68 | J12: =IF(COUNTIF($A$2:A12,A12)>1,"Duplicate","")
A13: ='Raw Store Exports'!A13 -> TXN00819 | B13: ='Raw Store Exports'!C13 -> 46064 | C13: =INDEX('Store Mapping'!$C$2:$C$19,MATCH(TRIM('Raw Store Exports'!B13),'Store Mapping'!$A$2:$A$19,0)) -> Eastgate | D13: ='Raw Store Exports'!D13 -> FTW-202 | E13: =INDEX('Product Master'!$B$2:$B$21,MATCH(D13,'Product Master'!$A$2:$A$21,0)) -> Canvas Low-Top | F13: =INDEX('Product Master'!$C$2:$C$21,MATCH(D13,'Product Master'!$A$2:$A$21,0)) -> Footwear | G13: =VALUE(TRIM('Raw Store Exports'!E13&"")) -> 6 | H13: =INDEX('Product Master'!$D$2:$D$21,MATCH(D13,'Product Master'!$A$2:$A$21,0)) -> 55 | I13: =G13*H13 -> 330 | J13: =IF(COUNTIF($A$2:A13,A13)>1,"Duplicate","")
... A1242: ='Raw Store Exports'!A1242 -> TXN00090 | B1242: ='Raw Store Exports'!C1242 -> 46031 | C1242: =INDEX('Store Mapping'!$C$2:$C$19,MATCH(TRIM('Raw Store Exports'!B1242),'Store Mapping'!$A$2:$A$19,0)) -> Northpark | D1242: ='Raw Store Exports'!D1242 -> APP-103 | E1242: =INDEX('Product Master'!$B$2:$B$21,MATCH(D1242,'Product Master'!$A$2:$A$21,0)) -> Fleece Pullover Hoodie | F1242: =INDEX('Product Master'!$C$2:$C$21,MATCH(D1242,'Product Master'!$A$2:$A$21,0)) -> Apparel | G1242: =VALUE(TRIM('Raw Store Exports'!E1242&"")) -> 2 | H1242: =INDEX('Product Master'!$D$2:$D$21,MATCH(D1242,'Product Master'!$A$2:$A$21,0)) -> 45 | I1242: =G1242*H1242 -> 90 | J1242: =IF(COUNTIF($A$2:A1242,A1242)>1,"Duplicate","")
H1244: Total Revenue (excl. duplicates) | I1244: =SUMIFS(I2:I1242,J2:J1242,"") -> 188741
H1245: Duplicate Rows Found | I1245: =COUNTIF(J2:J1242,"Duplicate") -> 47
H1246: Clean Transaction Count | I1246: =COUNTIF(J2:J1242,"") -> 1194

Sheet Raw Store Exports
A1: Transaction ID | B1: Store Label (raw) | C1: Date | D1: SKU | E1: Units (raw)
A2: TXN01054 | B2: downtown | C2: 46079 | D2: ELE-404 | E2: 1
A3: TXN00098 | B3: Riverside | C3: 46032 | D3: ACC-304 | E3: 6
A4: TXN00570 | B4: Airport Plaza | C4: 46048 | D4: HOM-504 | E4: 4
A5: TXN00369 | B5: NORTHPARK | C5: 46043 | D5: HOM-501 | E5: 2
A6: TXN00974 | B6: Eastgate | C6: 46075 | D6: ELE-401 | E6: 6
A7: TXN00623 | B7: Westside Mall | C7: 46055 | D7: ACC-303 | E7: 1
A8: TXN00930 | B8: WESTSIDE MALL | C8: 46073 | D8: ELE-401 | E8: 2
A9: TXN00449 | B9: downtown | C9: 46049 | D9: ELE-402 | E9: 1
A10: TXN01023 | B10: Riverside | C10: 46069 | D10: APP-101 | E10: 2
A11: TXN00639 | B11: westside mall | C11: 46056 | D11: HOM-502 | E11: 3
A12: TXN00316 | B12: westside mall | C12: 46043 | D12: APP-101 | E12: 1
A13: TXN00819 | B13: Eastgate | C13: 46064 | D13: FTW-202 | E13: 6
... A1242: TXN00090 | B1242: NORTHPARK | C1242: 46031 | D1242: APP-103 | E1242: 2

Sheet Store Mapping
A1: Raw Store Label | B1: Store ID | C1: Standard Store Name
A2: Downtown | B2: S01 | C2: Downtown
A3: DOWNTOWN STORE | B3: S01 | C3: Downtown
A4: downtown | B4: S01 | C4: Downtown
A5: Westside Mall | B5: S02 | C5: Westside Mall
A6: WESTSIDE MALL | B6: S02 | C6: Westside Mall
A7: westside mall | B7: S02 | C7: Westside Mall
A8: Eastgate | B8: S03 | C8: Eastgate
A9: EASTGATE STORE | B9: S03 | C9: Eastgate
A10: Eastgate | B10: S03 | C10: Eastgate
A11: Northpark | B11: S04 | C11: Northpark
A12: NORTHPARK | B12: S04 | C12: Northpark
... A19: airport plaza | B19: S06 | C19: Airport Plaza

Sheet Product Master
A1: SKU | B1: Product | C1: Category | D1: Unit Price | E1: Unit Cost
A2: APP-101 | B2: Classic Denim Jacket | C2: Apparel | D2: 68 | E2: 27.5
A3: APP-102 | B3: Cotton Crew T-Shirt | C3: Apparel | D3: 18 | E3: 6.5
A4: APP-103 | B4: Fleece Pullover Hoodie | C4: Apparel | D4: 45 | E4: 18
A5: APP-104 | B5: Slim Fit Chinos | C5: Apparel | D5: 52 | E5: 21
A6: FTW-201 | B6: Running Sneakers | C6: Footwear | D6: 89 | E6: 38
A7: FTW-202 | B7: Canvas Low-Top | C7: Footwear | D7: 55 | E7: 22
A8: FTW-203 | B8: Leather Ankle Boot | C8: Footwear | D8: 120 | E8: 52
A9: FTW-204 | B9: Slide Sandals | C9: Footwear | D9: 25 | E9: 9
A10: ACC-301 | B10: Leather Belt | C10: Accessories | D10: 30 | E10: 11
A11: ACC-302 | B11: Aviator Sunglasses | C11: Accessories | D11: 42 | E11: 15
A12: ACC-303 | B12: Canvas Tote Bag | C12: Accessories | D12: 24 | E12: 8.5
A13: ACC-304 | B13: Wool Beanie | C13: Accessories | D13: 16 | E13: 5.5
... A21: HOM-504 | B21: Bamboo Cutting Board | C21: Home Goods | D21: 27 | E21: 10

Sheet Calendar
A1: Date | B1: Year | C1: Month | D1: Month Name | E1: Quarter | F1: Week of Year | G1: Day of Week
A2: 46027 | B2: =YEAR(A2) -> 2026 | C2: =MONTH(A2) -> 1 | D2: =TEXT(A2,"mmm") -> Jan | E2: =ROUNDUP(MONTH(A2)/3,0) -> 1 | F2: =WEEKNUM(A2,1) -> 2 | G2: =TEXT(A2,"ddd") -> Mon
A3: 46028 | B3: =YEAR(A3) -> 2026 | C3: =MONTH(A3) -> 1 | D3: =TEXT(A3,"mmm") -> Jan | E3: =ROUNDUP(MONTH(A3)/3,0) -> 1 | F3: =WEEKNUM(A3,1) -> 2 | G3: =TEXT(A3,"ddd") -> Tue
A4: 46029 | B4: =YEAR(A4) -> 2026 | C4: =MONTH(A4) -> 1 | D4: =TEXT(A4,"mmm") -> Jan | E4: =ROUNDUP(MONTH(A4)/3,0) -> 1 | F4: =WEEKNUM(A4,1) -> 2 | G4: =TEXT(A4,"ddd") -> Wed
A5: 46030 | B5: =YEAR(A5) -> 2026 | C5: =MONTH(A5) -> 1 | D5: =TEXT(A5,"mmm") -> Jan | E5: =ROUNDUP(MONTH(A5)/3,0) -> 1 | F5: =WEEKNUM(A5,1) -> 2 | G5: =TEXT(A5,"ddd") -> Thu
A6: 46031 | B6: =YEAR(A6) -> 2026 | C6: =MONTH(A6) -> 1 | D6: =TEXT(A6,"mmm") -> Jan | E6: =ROUNDUP(MONTH(A6)/3,0) -> 1 | F6: =WEEKNUM(A6,1) -> 2 | G6: =TEXT(A6,"ddd") -> Fri
A7: 46032 | B7: =YEAR(A7) -> 2026 | C7: =MONTH(A7) -> 1 | D7: =TEXT(A7,"mmm") -> Jan | E7: =ROUNDUP(MONTH(A7)/3,0) -> 1 | F7: =WEEKNUM(A7,1) -> 2 | G7: =TEXT(A7,"ddd") -> Sat
A8: 46033 | B8: =YEAR(A8) -> 2026 | C8: =MONTH(A8) -> 1 | D8: =TEXT(A8,"mmm") -> Jan | E8: =ROUNDUP(MONTH(A8)/3,0) -> 1 | F8: =WEEKNUM(A8,1) -> 3 | G8: =TEXT(A8,"ddd") -> Sun
A9: 46034 | B9: =YEAR(A9) -> 2026 | C9: =MONTH(A9) -> 1 | D9: =TEXT(A9,"mmm") -> Jan | E9: =ROUNDUP(MONTH(A9)/3,0) -> 1 | F9: =WEEKNUM(A9,1) -> 3 | G9: =TEXT(A9,"ddd") -> Mon
A10: 46035 | B10: =YEAR(A10) -> 2026 | C10: =MONTH(A10) -> 1 | D10: =TEXT(A10,"mmm") -> Jan | E10: =ROUNDUP(MONTH(A10)/3,0) -> 1 | F10: =WEEKNUM(A10,1) -> 3 | G10: =TEXT(A10,"ddd") -> Tue
A11: 46036 | B11: =YEAR(A11) -> 2026 | C11: =MONTH(A11) -> 1 | D11: =TEXT(A11,"mmm") -> Jan | E11: =ROUNDUP(MONTH(A11)/3,0) -> 1 | F11: =WEEKNUM(A11,1) -> 3 | G11: =TEXT(A11,"ddd") -> Wed
A12: 46037 | B12: =YEAR(A12) -> 2026 | C12: =MONTH(A12) -> 1 | D12: =TEXT(A12,"mmm") -> Jan | E12: =ROUNDUP(MONTH(A12)/3,0) -> 1 | F12: =WEEKNUM(A12,1) -> 3 | G12: =TEXT(A12,"ddd") -> Thu
A13: 46038 | B13: =YEAR(A13) -> 2026 | C13: =MONTH(A13) -> 1 | D13: =TEXT(A13,"mmm") -> Jan | E13: =ROUNDUP(MONTH(A13)/3,0) -> 1 | F13: =WEEKNUM(A13,1) -> 3 | G13: =TEXT(A13,"ddd") -> Fri
... A57: 46082 | B57: =YEAR(A57) -> 2026 | C57: =MONTH(A57) -> 3 | D57: =TEXT(A57,"mmm") -> Mar | E57: =ROUNDUP(MONTH(A57)/3,0) -> 1 | F57: =WEEKNUM(A57,1) -> 10 | G57: =TEXT(A57,"ddd") -> Sun

Sheet Measures (DAX vs Excel)
A1: Measure | B1: DAX (Power Pivot) | C1: Excel Formula Equivalent | D1: Result
A2: Total Revenue | B2: Total Revenue := SUMX(Sales, Sales[Units] * RELATED(Product[UnitPrice])) | C2: =SUMIFS('Consolidated Master'!I2:I1242,'Consolidated Master'!J2:J1242,"") -> 188741 | D2: =C2 -> 188741
A3: Revenue — Downtown | B3: Downtown Revenue := CALCULATE([Total Revenue], Store[StoreName]="Downtown") | C3: =SUMIFS('Consolidated Master'!I2:I1242,'Consolidated Master'!C2:C1242,"Downtown",'Consolidated Master'!J2:J1242,"") -> 32760 | D3: =C3 -> 32760
A4: Revenue — Footwear | B4: Footwear Revenue := CALCULATE([Total Revenue], Product[Category]="Footwear") | C4: =SUMIFS('Consolidated Master'!I2:I1242,'Consolidated Master'!F2:F1242,"Footwear",'Consolidated Master'!J2:J1242,"") -> 57772 | D4: =C4 -> 57772
A5: Total Units Sold | B5: Total Units := SUM(Sales[Units]) | C5: =SUMIFS('Consolidated Master'!G2:G1242,'Consolidated Master'!J2:J1242,"") -> 4133 | D5: =C5 -> 4133
A6: Avg Revenue per Transaction | B6: Avg Txn Value := DIVIDE([Total Revenue], COUNTROWS(Sales)) | C6: =IFERROR(D2/COUNTIF('Consolidated Master'!J2:J1242,""),0) -> 158.07454 | D6: =C6 -> 158.07454
A7: Stores Reporting | B7: Store Count := DISTINCTCOUNT(Sales[Store]) | C7: =SUMPRODUCT(1/COUNTIF('Store Mapping'!$C$2:$C$19,'Store Mapping'!$C$2:$C$19)) -> 6 | D7: =C7 -> 6

Sheet Power Query Steps
A1: How to automate this for real: Power Query recipe
A2: In live Excel, this whole pipeline can run itself every time new CSVs land in a folder. Here's the step list — Data > Get Data > From File > From Folder, pointed at the folder your stores drop their weekly exports into:
A4: 1. Get Data > From Folder | B4: Point Power Query at the shared folder where all store CSVs land.
A5: 2. Combine & Transform | B5: Power Query stacks every CSV in the folder into one table automatically — new files picked up on next refresh, no formula changes needed.
A6: 3. Promote Headers | B6: Use the first row of each file as column headers.
A7: 4. Trim & Clean columns | B7: Transform > Format > Trim / Clean on the Store Label column; Change Type > Whole Number on Units (Power Query auto-parses the stray whitespace this workbook handles with TRIM/VALUE).
A8: 5. Merge with Store Mapping | B8: Home > Merge Queries, join on the raw Store Label, expand the Standard Store Name column — replaces the INDEX/MATCH used here.
A9: 6. Merge with Product Master | B9: Merge Queries again on SKU, expand Product/Category/UnitPrice/UnitCost.
A10: 7. Add Custom Column: Revenue | B10: Add Column > Custom Column: [Clean Units] * [Unit Price].
A11: 8. Remove Duplicates | B11: Select the Transaction ID column > Remove Rows > Remove Duplicates.
A12: 9. Close & Load To > Data Model | B12: Loads the cleaned table into Power Pivot, ready for DAX measures and PivotTables.
A13: 10. Refresh All | B13: Data > Refresh All (or the VBA macro on the next sheet) re-runs every step above against whatever files are currently in the folder.

Sheet Refresh Macro
A1: One-click refresh: VBA macro
A2: Paste this into a real Excel workbook's VBA editor (Alt+F11 > Insert > Module) once the Power Query steps above are set up, then assign it to a button (Developer tab > Insert > Button) so anyone can refresh with one click — no need to know Data > Refresh All exists.
A4: Sub RefreshAllData()
A5: ' One-click refresh: pulls in any new CSVs dropped into the export folder,
A6: ' re-runs every Power Query step, and recalculates the workbook.
A8: Application.ScreenUpdating = False
A9: Application.StatusBar = "Refreshing store data..."
A11: On Error GoTo ErrorHandler
A13: ' Refresh every query and PivotTable connection in the workbook
A14: ThisWorkbook.RefreshAll
A16: ' Give Power Query a moment to finish before recalculating
A17: Application.CalculateFullRebuild
... A31: Tip: record a blank macro first (Developer > Record Macro) to confirm your security settings allow macros, then replace its body with the code above.
