Workbook

Sheet README
B2: Markdown & Promotion Impact Simulator
B4: Business Problem
B5: Should a category get a 10%, 20%, or 30% discount — and what does each option do to margin? A markdown grows units sold (demand curves down as price drops) but shrinks the margin on every unit. Whether a given discount helps or hurts total profit depends on how price-sensitive that category's customers are.
B7: Excel Skills Demonstrated
B8: • One-variable sensitivity table: profit/revenue across a range of discount levels
B9: • Two-variable sensitivity grid: discount level x category, profit impact at every combination
B10: • Break-even discount solved algebraically (a closed-form Goal Seek)
B11: • Scenario comparison table (a Scenario-Manager-style summary) across named promo options
B12: • Data validation dropdown to switch the active category
B13: • Sensitivity charts and conditional-formatting heat maps
B15: The Model
B16: Price elasticity of demand (E) says how much unit volume rises for a given % price cut: %ΔVolume = E x %ΔPrice-cut. E = 2.0 means a 10% price cut lifts volume ~20%. Elasticity differs by category — Footwear customers are assumed far more price-sensitive than Electronics buyers, for example.
... B32: Source: category price/cost derived from the shared product master used across this repo; baseline volume and elasticity are illustrative assumptions, not measured figures. Replace them on Category Assumptions with real numbers and every sheet recalculates.

Sheet Dashboard
B2: Markdown & Promotion Impact Dashboard
B3: ="Category: "&'Markdown Model'!$C$5&" | Discount: "&TEXT('Markdown Model'!$C$6,"0%") -> Category: Apparel | Discount: 20%
B5: Profit Change $ (current) | D5: Profit Change % (current) | F5: Break-even Discount % | H5: Recommended Max Discount
B6: ='Markdown Model'!$C$20 -> -966.72 | D6: ='Markdown Model'!$C$21 -> -0.092509091 | F6: ='Markdown Model'!$F$5 -> 0.045537341 | H6: ='Markdown Model'!$F$6 -> 0
B9: Tip: change the category and discount % on the Markdown Model sheet — every chart and table here updates automatically.

Sheet Markdown Model
B2: Markdown Impact Calculator
B3: Change the blue cells to test any category / discount combination.
B5: Selected Category | C5: Apparel | E5: Break-even Discount % | F5: =INDEX('Category Assumptions'!$G$2:$G$6,MATCH($C$5,'Category Assumptions'!$A$2:$A$6,0)) -> 0.045537341
B6: Discount % | C6: 0.2 | E6: Recommended Max Discount | F6: =MAX(F5-0.05,0) -> 0
E8: How to read this
B9: Baseline Unit Price | C9: =INDEX('Category Assumptions'!$B$2:$B$6,MATCH($C$5,'Category Assumptions'!$A$2:$A$6,0)) -> 45.75 | E9: If Profit Change % (C21) is negative, this discount destroys profit even though revenue likely rose — the volume lift isn't enough to cover the margin given up per unit. Compare the Discount % to Break-even Discount % above.
B10: Baseline Unit Cost | C10: =INDEX('Category Assumptions'!$C$2:$C$6,MATCH($C$5,'Category Assumptions'!$A$2:$A$6,0)) -> 18.25
B11: Baseline Monthly Units | C11: =INDEX('Category Assumptions'!$E$2:$E$6,MATCH($C$5,'Category Assumptions'!$A$2:$A$6,0)) -> 380
B12: Price Elasticity | C12: =INDEX('Category Assumptions'!$F$2:$F$6,MATCH($C$5,'Category Assumptions'!$A$2:$A$6,0)) -> 1.8
B13: New Price | C13: =C9*(1-$C$6) -> 36.6
B14: Volume Lift % | C14: =C12*$C$6 -> 0.36
B15: New Monthly Units | C15: =C11*(1+C14) -> 516.8
B16: Baseline Revenue | C16: =C9*C11 -> 17385
B17: Baseline Profit | C17: =(C9-C10)*C11 -> 10450
B18: New Revenue | C18: =C13*C15 -> 18914.88
B19: New Profit | C19: =(C13-C10)*C15 -> 9483.28
B20: Profit Change $ | C20: =C19-C17 -> -966.72
B21: Profit Change % | C21: =C20/C17 -> -0.092509091

Sheet Category Assumptions
A1: Category | B1: Avg Unit Price | C1: Avg Unit Cost | D1: Margin % | E1: Baseline Monthly Units | F1: Price Elasticity | G1: Break-even Discount %
A2: Apparel | B2: 45.75 | C2: 18.25 | D2: =(B2-C2)/B2 -> 0.6010929 | E2: 380 | F2: 1.8 | G2: =D2-1/F2 -> 0.045537341
A3: Footwear | B3: 72.25 | C3: 30.25 | D3: =(B3-C3)/B3 -> 0.58131488 | E3: 340 | F3: 2.2 | G3: =D3-1/F3 -> 0.12676942
A4: Accessories | B4: 28 | C4: 10 | D4: =(B4-C4)/B4 -> 0.64285714 | E4: 300 | F4: 1.5 | G4: =D4-1/F4 -> -0.023809524
A5: Electronics | B5: 62.25 | C5: 25.88 | D5: =(B5-C5)/B5 -> 0.58425703 | E5: 260 | F5: 1.3 | G5: =D5-1/F5 -> -0.18497374
A6: Home Goods | B6: 25.5 | C6: 9.5 | D6: =(B6-C6)/B6 -> 0.62745098 | E6: 220 | F6: 1.6 | G6: =D6-1/F6 -> 0.0024509804

Sheet One-Variable Sensitivity
A1: One-Variable Sensitivity — varies Discount % for the category currently selected on Markdown Model
A2: Discount % | B2: New Volume | C2: Revenue | D2: Profit | E2: Profit Change %
A3: 0 | B3: ='Markdown Model'!$C$11*(1+'Markdown Model'!$C$12*A3) -> 380 | C3: =('Markdown Model'!$C$9*(1-A3))*B3 -> 17385 | D3: =(('Markdown Model'!$C$9*(1-A3))-'Markdown Model'!$C$10)*B3 -> 10450 | E3: =(D3-'Markdown Model'!$C$17)/'Markdown Model'!$C$17 -> 0
A4: 0.02 | B4: ='Markdown Model'!$C$11*(1+'Markdown Model'!$C$12*A4) -> 393.68 | C4: =('Markdown Model'!$C$9*(1-A4))*B4 -> 17650.643 | D4: =(('Markdown Model'!$C$9*(1-A4))-'Markdown Model'!$C$10)*B4 -> 10465.983 | E4: =(D4-'Markdown Model'!$C$17)/'Markdown Model'!$C$17 -> 0.0015294545
A5: 0.04 | B5: ='Markdown Model'!$C$11*(1+'Markdown Model'!$C$12*A5) -> 407.36 | C5: =('Markdown Model'!$C$9*(1-A5))*B5 -> 17891.251 | D5: =(('Markdown Model'!$C$9*(1-A5))-'Markdown Model'!$C$10)*B5 -> 10456.931 | E5: =(D5-'Markdown Model'!$C$17)/'Markdown Model'!$C$17 -> 0.00066327273
A6: 0.06 | B6: ='Markdown Model'!$C$11*(1+'Markdown Model'!$C$12*A6) -> 421.04 | C6: =('Markdown Model'!$C$9*(1-A6))*B6 -> 18106.825 | D6: =(('Markdown Model'!$C$9*(1-A6))-'Markdown Model'!$C$10)*B6 -> 10422.845 | E6: =(D6-'Markdown Model'!$C$17)/'Markdown Model'!$C$17 -> -0.0025985455
A7: 0.08 | B7: ='Markdown Model'!$C$11*(1+'Markdown Model'!$C$12*A7) -> 434.72 | C7: =('Markdown Model'!$C$9*(1-A7))*B7 -> 18297.365 | D7: =(('Markdown Model'!$C$9*(1-A7))-'Markdown Model'!$C$10)*B7 -> 10363.725 | E7: =(D7-'Markdown Model'!$C$17)/'Markdown Model'!$C$17 -> -0.008256
A8: 0.1 | B8: ='Markdown Model'!$C$11*(1+'Markdown Model'!$C$12*A8) -> 448.4 | C8: =('Markdown Model'!$C$9*(1-A8))*B8 -> 18462.87 | D8: =(('Markdown Model'!$C$9*(1-A8))-'Markdown Model'!$C$10)*B8 -> 10279.57 | E8: =(D8-'Markdown Model'!$C$17)/'Markdown Model'!$C$17 -> -0.016309091
A9: 0.12 | B9: ='Markdown Model'!$C$11*(1+'Markdown Model'!$C$12*A9) -> 462.08 | C9: =('Markdown Model'!$C$9*(1-A9))*B9 -> 18603.341 | D9: =(('Markdown Model'!$C$9*(1-A9))-'Markdown Model'!$C$10)*B9 -> 10170.381 | E9: =(D9-'Markdown Model'!$C$17)/'Markdown Model'!$C$17 -> -0.026757818
A10: 0.14 | B10: ='Markdown Model'!$C$11*(1+'Markdown Model'!$C$12*A10) -> 475.76 | C10: =('Markdown Model'!$C$9*(1-A10))*B10 -> 18718.777 | D10: =(('Markdown Model'!$C$9*(1-A10))-'Markdown Model'!$C$10)*B10 -> 10036.157 | E10: =(D10-'Markdown Model'!$C$17)/'Markdown Model'!$C$17 -> -0.039602182
A11: 0.16 | B11: ='Markdown Model'!$C$11*(1+'Markdown Model'!$C$12*A11) -> 489.44 | C11: =('Markdown Model'!$C$9*(1-A11))*B11 -> 18809.179 | D11: =(('Markdown Model'!$C$9*(1-A11))-'Markdown Model'!$C$10)*B11 -> 9876.8992 | E11: =(D11-'Markdown Model'!$C$17)/'Markdown Model'!$C$17 -> -0.054842182
A12: 0.18 | B12: ='Markdown Model'!$C$11*(1+'Markdown Model'!$C$12*A12) -> 503.12 | C12: =('Markdown Model'!$C$9*(1-A12))*B12 -> 18874.547 | D12: =(('Markdown Model'!$C$9*(1-A12))-'Markdown Model'!$C$10)*B12 -> 9692.6068 | E12: =(D12-'Markdown Model'!$C$17)/'Markdown Model'!$C$17 -> -0.072477818
A13: 0.2 | B13: ='Markdown Model'!$C$11*(1+'Markdown Model'!$C$12*A13) -> 516.8 | C13: =('Markdown Model'!$C$9*(1-A13))*B13 -> 18914.88 | D13: =(('Markdown Model'!$C$9*(1-A13))-'Markdown Model'!$C$10)*B13 -> 9483.28 | E13: =(D13-'Markdown Model'!$C$17)/'Markdown Model'!$C$17 -> -0.092509091
A14: 0.22 | B14: ='Markdown Model'!$C$11*(1+'Markdown Model'!$C$12*A14) -> 530.48 | C14: =('Markdown Model'!$C$9*(1-A14))*B14 -> 18930.179 | D14: =(('Markdown Model'!$C$9*(1-A14))-'Markdown Model'!$C$10)*B14 -> 9248.9188 | E14: =(D14-'Markdown Model'!$C$17)/'Markdown Model'!$C$17 -> -0.114936
... A23: 0.4 | B23: ='Markdown Model'!$C$11*(1+'Markdown Model'!$C$12*A23) -> 653.6 | C23: =('Markdown Model'!$C$9*(1-A23))*B23 -> 17941.32 | D23: =(('Markdown Model'!$C$9*(1-A23))-'Markdown Model'!$C$10)*B23 -> 6013.12 | E23: =(D23-'Markdown Model'!$C$17)/'Markdown Model'!$C$17 -> -0.42458182

Sheet Two-Variable Grid
A1: Two-Variable Grid — Profit Change % by Discount % (rows) x Category (columns)
A2: Discount % | B2: Apparel | C2: Footwear | D2: Accessories | E2: Electronics | F2: Home Goods
A3: 0 | B3: =(((INDEX('Category Assumptions'!$B$2:$B$6,MATCH(B$2,'Category Assumptions'!$A$2:$A$6,0))*(1-$A3))-INDEX('Category Assumptions'!$C$2:$C$6,MATCH(B$2,'Category Assumptions'!$A$2:$A$6,0)))*(INDEX('Category Assumptions'!$E$2:$E$6,MATCH(B$2,'Category Assumptions'!$A$2:$A$6,0))*(1+INDEX('Category Assumptions'!$F$2:$F$6,MATCH(B$2,'Category Assumptions'!$A$2:$A$6,0))*$A3))-((INDEX('Category Assumptions'!$B$2:$B$6,MATCH(B$2,'Category Assumptions'!$A$2:$A$6,0))-INDEX('Category Assumptions'!$C$2:$C$6,MATCH(B$2,'Category Assumptions'!$A$2:$A$6,0)))*INDEX('Category Assumptions'!$E$2:$E$6,MATCH(B$2,'Category Assumptions'!$A$2:$A$6,0))))/((INDEX('Category Assumptions'!$B$2:$B$6,MATCH(B$2,'Category Assumptions'!$A$2:$A$6,0))-INDEX('Category Assumptions'!$C$2:$C$6,MATCH(B$2,'Category Assumptions'!$A$2:$A$6,0)))*INDEX('Category Assumptions'!$E$2:$E$6,MATCH(B$2,'Category Assumptions'!$A$2:$A$6,0))) -> 0 | C3: =(((INDEX('Category Assumptions'!$B$2:$B$6,MATCH(C$2,'Category Assumptions'!$A$2:$A$6,0))*(1-$A3))-INDEX('Category Assumptions'!$C$2:$C$6,MATCH(C$2,'Category Assumptions'!$A$2:$A$6,0)))*(INDEX('Category Assumptions'!$E$2:$E$6,MATCH(C$2,'Category Assumptions'!$A$2:$A$6,0))*(1+INDEX('Category Assumptions'!$F$2:$F$6,MATCH(C$2,'Category Assumptions'!$A$2:$A$6,0))*$A3))-((INDEX('Category Assumptions'!$B$2:$B$6,MATCH(C$2,'Category Assumptions'!$A$2:$A$6,0))-INDEX('Category Assumptions'!$C$2:$C$6,MATCH(C$2,'Category Assumptions'!$A$2:$A$6,0)))*INDEX('Category Assumptions'!$E$2:$E$6,MATCH(C$2,'Category Assumptions'!$A$2:$A$6,0))))/((INDEX('Category Assumptions'!$B$2:$B$6,MATCH(C$2,'Category Assumptions'!$A$2:$A$6,0))-INDEX('Category Assumptions'!$C$2:$C$6,MATCH(C$2,'Category Assumptions'!$A$2:$A$6,0)))*INDEX('Category Assumptions'!$E$2:$E$6,MATCH(C$2,'Category Assumptions'!$A$2:$A$6,0))) -> 0 | D3: =(((INDEX('Category Assumptions'!$B$2:$B$6,MATCH(D$2,'Category Assumptions'!$A$2:$A$6,0))*(1-$A3))-INDEX('Category Assumptions'!$C$2:$C$6,MATCH(D$2,'Category Assumptions'!$A$2:$A$6,0)))*(INDEX('Category Assumptions'!$E$2:$E$6,MATCH(D$2,'Category Assumptions'!$A$2:$A$6,0))*(1+INDEX('Category Assumptions'!$F$2:$F$6,MATCH(D$2,'Category Assumptions'!$A$2:$A$6,0))*$A3))-((INDEX('Category Assumptions'!$B$2:$B$6,MATCH(D$2,'Category Assumptions'!$A$2:$A$6,0))-INDEX('Category Assumptions'!$C$2:$C$6,MATCH(D$2,'Category Assumptions'!$A$2:$A$6,0)))*INDEX('Category Assumptions'!$E$2:$E$6,MATCH(D$2,'Category Assumptions'!$A$2:$A$6,0))))/((INDEX('Category Assumptions'!$B$2:$B$6,MATCH(D$2,'Category Assumptions'!$A$2:$A$6,0))-INDEX('Category Assumptions'!$C$2:$C$6,MATCH(D$2,'Category Assumptions'!$A$2:$A$6,0)))*INDEX('Category Assumptions'!$E$2:$E$6,MATCH(D$2,'Category Assumptions'!$A$2:$A$6,0))) -> 0 | E3: =(((INDEX('Category Assumptions'!$B$2:$B$6,MATCH(E$2,'Category Assumptions'!$A$2:$A$6,0))*(1-$A3))-INDEX('Category Assumptions'!$C$2:$C$6,MATCH(E$2,'Category Assumptions'!$A$2:$A$6,0)))*(INDEX('Category Assumptions'!$E$2:$E$6,MATCH(E$2,'Category Assumptions'!$A$2:$A$6,0))*(1+INDEX('Category Assumptions'!$F$2:$F$6,MATCH(E$2,'Category Assumptions'!$A$2:$A$6,0))*$A3))-((INDEX('Category Assumptions'!$B$2:$B$6,MATCH(E$2,'Category Assumptions'!$A$2:$A$6,0))-INDEX('Category Assumptions'!$C$2:$C$6,MATCH(E$2,'Category Assumptions'!$A$2:$A$6,0)))*INDEX('Category Assumptions'!$E$2:$E$6,MATCH(E$2,'Category Assumptions'!$A$2:$A$6,0))))/((INDEX('Category Assumptions'!$B$2:$B$6,MATCH(E$2,'Category Assumptions'!$A$2:$A$6,0))-INDEX('Category Assumptions'!$C$2:$C$6,MATCH(E$2,'Category Assumptions'!$A$2:$A$6,0)))*INDEX('Category Assumptions'!$E$2:$E$6,MATCH(E$2,'Category Assumptions'!$A$2:$A$6,0))) -> 0 | F3: =(((INDEX('Category Assumptions'!$B$2:$B$6,MATCH(F$2,'Category Assumptions'!$A$2:$A$6,0))*(1-$A3))-INDEX('Category Assumptions'!$C$2:$C$6,MATCH(F$2,'Category Assumptions'!$A$2:$A$6,0)))*(INDEX('Category Assumptions'!$E$2:$E$6,MATCH(F$2,'Category Assumptions'!$A$2:$A$6,0))*(1+INDEX('Category Assumptions'!$F$2:$F$6,MATCH(F$2,'Category Assumptions'!$A$2:$A$6,0))*$A3))-((INDEX('Category Assumptions'!$B$2:$B$6,MATCH(F$2,'Category Assumptions'!$A$2:$A$6,0))-INDEX('Category Assumptions'!$C$2:$C$6,MATCH(F$2,'Category Assumptions'!$A$2:$A$6,0)))*INDEX('Category Assumptions'!$E$2:$E$6,MATCH(F$2,'Category Assumptions'!$A$2:$A$6,0))))/((INDEX('Category Assumptions'!$B$2:$B$6,MATCH(F$2,'Category Assumptions'!$A$2:$A$6,0))-INDEX('Category Assumptions'!$C$2:$C$6,MATCH(F$2,'Category Assumptions'!$A$2:$A$6,0)))*INDEX('Category Assumptions'!$E$2:$E$6,MATCH(F$2,'Category Assumptions'!$A$2:$A$6,0))) -> 0
A4: 0.05 | B4: =(((INDEX('Category Assumptions'!$B$2:$B$6,MATCH(B$2,'Category Assumptions'!$A$2:$A$6,0))*(1-$A4))-INDEX('Category Assumptions'!$C$2:$C$6,MATCH(B$2,'Category Assumptions'!$A$2:$A$6,0)))*(INDEX('Category Assumptions'!$E$2:$E$6,MATCH(B$2,'Category Assumptions'!$A$2:$A$6,0))*(1+INDEX('Category Assumptions'!$F$2:$F$6,MATCH(B$2,'Category Assumptions'!$A$2:$A$6,0))*$A4))-((INDEX('Category Assumptions'!$B$2:$B$6,MATCH(B$2,'Category Assumptions'!$A$2:$A$6,0))-INDEX('Category Assumptions'!$C$2:$C$6,MATCH(B$2,'Category Assumptions'!$A$2:$A$6,0)))*INDEX('Category Assumptions'!$E$2:$E$6,MATCH(B$2,'Category Assumptions'!$A$2:$A$6,0))))/((INDEX('Category Assumptions'!$B$2:$B$6,MATCH(B$2,'Category Assumptions'!$A$2:$A$6,0))-INDEX('Category Assumptions'!$C$2:$C$6,MATCH(B$2,'Category Assumptions'!$A$2:$A$6,0)))*INDEX('Category Assumptions'!$E$2:$E$6,MATCH(B$2,'Category Assumptions'!$A$2:$A$6,0))) -> -0.00066818182 | C4: =(((INDEX('Category Assumptions'!$B$2:$B$6,MATCH(C$2,'Category Assumptions'!$A$2:$A$6,0))*(1-$A4))-INDEX('Category Assumptions'!$C$2:$C$6,MATCH(C$2,'Category Assumptions'!$A$2:$A$6,0)))*(INDEX('Category Assumptions'!$E$2:$E$6,MATCH(C$2,'Category Assumptions'!$A$2:$A$6,0))*(1+INDEX('Category Assumptions'!$F$2:$F$6,MATCH(C$2,'Category Assumptions'!$A$2:$A$6,0))*$A4))-((INDEX('Category Assumptions'!$B$2:$B$6,MATCH(C$2,'Category Assumptions'!$A$2:$A$6,0))-INDEX('Category Assumptions'!$C$2:$C$6,MATCH(C$2,'Category Assumptions'!$A$2:$A$6,0)))*INDEX('Category Assumptions'!$E$2:$E$6,MATCH(C$2,'Category Assumptions'!$A$2:$A$6,0))))/((INDEX('Category Assumptions'!$B$2:$B$6,MATCH(C$2,'Category Assumptions'!$A$2:$A$6,0))-INDEX('Category Assumptions'!$C$2:$C$6,MATCH(C$2,'Category Assumptions'!$A$2:$A$6,0)))*INDEX('Category Assumptions'!$E$2:$E$6,MATCH(C$2,'Category Assumptions'!$A$2:$A$6,0))) -> 0.014526786 | D4: =(((INDEX('Category Assumptions'!$B$2:$B$6,MATCH(D$2,'Category Assumptions'!$A$2:$A$6,0))*(1-$A4))-INDEX('Category Assumptions'!$C$2:$C$6,MATCH(D$2,'Category Assumptions'!$A$2:$A$6,0)))*(INDEX('Category Assumptions'!$E$2:$E$6,MATCH(D$2,'Category Assumptions'!$A$2:$A$6,0))*(1+INDEX('Category Assumptions'!$F$2:$F$6,MATCH(D$2,'Category Assumptions'!$A$2:$A$6,0))*$A4))-((INDEX('Category Assumptions'!$B$2:$B$6,MATCH(D$2,'Category Assumptions'!$A$2:$A$6,0))-INDEX('Category Assumptions'!$C$2:$C$6,MATCH(D$2,'Category Assumptions'!$A$2:$A$6,0)))*INDEX('Category Assumptions'!$E$2:$E$6,MATCH(D$2,'Category Assumptions'!$A$2:$A$6,0))))/((INDEX('Category Assumptions'!$B$2:$B$6,MATCH(D$2,'Category Assumptions'!$A$2:$A$6,0))-INDEX('Category Assumptions'!$C$2:$C$6,MATCH(D$2,'Category Assumptions'!$A$2:$A$6,0)))*INDEX('Category Assumptions'!$E$2:$E$6,MATCH(D$2,'Category Assumptions'!$A$2:$A$6,0))) -> -0.0086111111 | E4: =(((INDEX('Category Assumptions'!$B$2:$B$6,MATCH(E$2,'Category Assumptions'!$A$2:$A$6,0))*(1-$A4))-INDEX('Category Assumptions'!$C$2:$C$6,MATCH(E$2,'Category Assumptions'!$A$2:$A$6,0)))*(INDEX('Category Assumptions'!$E$2:$E$6,MATCH(E$2,'Category Assumptions'!$A$2:$A$6,0))*(1+INDEX('Category Assumptions'!$F$2:$F$6,MATCH(E$2,'Category Assumptions'!$A$2:$A$6,0))*$A4))-((INDEX('Category Assumptions'!$B$2:$B$6,MATCH(E$2,'Category Assumptions'!$A$2:$A$6,0))-INDEX('Category Assumptions'!$C$2:$C$6,MATCH(E$2,'Category Assumptions'!$A$2:$A$6,0)))*INDEX('Category Assumptions'!$E$2:$E$6,MATCH(E$2,'Category Assumptions'!$A$2:$A$6,0))))/((INDEX('Category Assumptions'!$B$2:$B$6,MATCH(E$2,'Category Assumptions'!$A$2:$A$6,0))-INDEX('Category Assumptions'!$C$2:$C$6,MATCH(E$2,'Category Assumptions'!$A$2:$A$6,0)))*INDEX('Category Assumptions'!$E$2:$E$6,MATCH(E$2,'Category Assumptions'!$A$2:$A$6,0))) -> -0.026141394 | F4: =(((INDEX('Category Assumptions'!$B$2:$B$6,MATCH(F$2,'Category Assumptions'!$A$2:$A$6,0))*(1-$A4))-INDEX('Category Assumptions'!$C$2:$C$6,MATCH(F$2,'Category Assumptions'!$A$2:$A$6,0)))*(INDEX('Category Assumptions'!$E$2:$E$6,MATCH(F$2,'Category Assumptions'!$A$2:$A$6,0))*(1+INDEX('Category Assumptions'!$F$2:$F$6,MATCH(F$2,'Category Assumptions'!$A$2:$A$6,0))*$A4))-((INDEX('Category Assumptions'!$B$2:$B$6,MATCH(F$2,'Category Assumptions'!$A$2:$A$6,0))-INDEX('Category Assumptions'!$C$2:$C$6,MATCH(F$2,'Category Assumptions'!$A$2:$A$6,0)))*INDEX('Category Assumptions'!$E$2:$E$6,MATCH(F$2,'Category Assumptions'!$A$2:$A$6,0))))/((INDEX('Category Assumptions'!$B$2:$B$6,MATCH(F$2,'Category Assumptions'!$A$2:$A$6,0))-INDEX('Category Assumptions'!$C$2:$C$6,MATCH(F$2,'Category Assumptions'!$A$2:$A$6,0)))*INDEX('Category Assumptions'!$E$2:$E$6,MATCH(F$2,'Category Assumptions'!$A$2:$A$6,0))) -> -0.0060625
A5: 0.1 | B5: =(((INDEX('Category Assumptions'!$B$2:$B$6,MATCH(B$2,'Category Assumptions'!$A$2:$A$6,0))*(1-$A5))-INDEX('Category Assumptions'!$C$2:$C$6,MATCH(B$2,'Category Assumptions'!$A$2:$A$6,0)))*(INDEX('Category Assumptions'!$E$2:$E$6,MATCH(B$2,'Category Assumptions'!$A$2:$A$6,0))*(1+INDEX('Category Assumptions'!$F$2:$F$6,MATCH(B$2,'Category Assumptions'!$A$2:$A$6,0))*$A5))-((INDEX('Category Assumptions'!$B$2:$B$6,MATCH(B$2,'Category Assumptions'!$A$2:$A$6,0))-INDEX('Category Assumptions'!$C$2:$C$6,MATCH(B$2,'Category Assumptions'!$A$2:$A$6,0)))*INDEX('Category Assumptions'!$E$2:$E$6,MATCH(B$2,'Category Assumptions'!$A$2:$A$6,0))))/((INDEX('Category Assumptions'!$B$2:$B$6,MATCH(B$2,'Category Assumptions'!$A$2:$A$6,0))-INDEX('Category Assumptions'!$C$2:$C$6,MATCH(B$2,'Category Assumptions'!$A$2:$A$6,0)))*INDEX('Category Assumptions'!$E$2:$E$6,MATCH(B$2,'Category Assumptions'!$A$2:$A$6,0))) -> -0.016309091 | C5: =(((INDEX('Category Assumptions'!$B$2:$B$6,MATCH(C$2,'Category Assumptions'!$A$2:$A$6,0))*(1-$A5))-INDEX('Category Assumptions'!$C$2:$C$6,MATCH(C$2,'Category Assumptions'!$A$2:$A$6,0)))*(INDEX('Category Assumptions'!$E$2:$E$6,MATCH(C$2,'Category Assumptions'!$A$2:$A$6,0))*(1+INDEX('Category Assumptions'!$F$2:$F$6,MATCH(C$2,'Category Assumptions'!$A$2:$A$6,0))*$A5))-((INDEX('Category Assumptions'!$B$2:$B$6,MATCH(C$2,'Category Assumptions'!$A$2:$A$6,0))-INDEX('Category Assumptions'!$C$2:$C$6,MATCH(C$2,'Category Assumptions'!$A$2:$A$6,0)))*INDEX('Category Assumptions'!$E$2:$E$6,MATCH(C$2,'Category Assumptions'!$A$2:$A$6,0))))/((INDEX('Category Assumptions'!$B$2:$B$6,MATCH(C$2,'Category Assumptions'!$A$2:$A$6,0))-INDEX('Category Assumptions'!$C$2:$C$6,MATCH(C$2,'Category Assumptions'!$A$2:$A$6,0)))*INDEX('Category Assumptions'!$E$2:$E$6,MATCH(C$2,'Category Assumptions'!$A$2:$A$6,0))) -> 0.010130952 | D5: =(((INDEX('Category Assumptions'!$B$2:$B$6,MATCH(D$2,'Category Assumptions'!$A$2:$A$6,0))*(1-$A5))-INDEX('Category Assumptions'!$C$2:$C$6,MATCH(D$2,'Category Assumptions'!$A$2:$A$6,0)))*(INDEX('Category Assumptions'!$E$2:$E$6,MATCH(D$2,'Category Assumptions'!$A$2:$A$6,0))*(1+INDEX('Category Assumptions'!$F$2:$F$6,MATCH(D$2,'Category Assumptions'!$A$2:$A$6,0))*$A5))-((INDEX('Category Assumptions'!$B$2:$B$6,MATCH(D$2,'Category Assumptions'!$A$2:$A$6,0))-INDEX('Category Assumptions'!$C$2:$C$6,MATCH(D$2,'Category Assumptions'!$A$2:$A$6,0)))*INDEX('Category Assumptions'!$E$2:$E$6,MATCH(D$2,'Category Assumptions'!$A$2:$A$6,0))))/((INDEX('Category Assumptions'!$B$2:$B$6,MATCH(D$2,'Category Assumptions'!$A$2:$A$6,0))-INDEX('Category Assumptions'!$C$2:$C$6,MATCH(D$2,'Category Assumptions'!$A$2:$A$6,0)))*INDEX('Category Assumptions'!$E$2:$E$6,MATCH(D$2,'Category Assumptions'!$A$2:$A$6,0))) -> -0.028888889 | E5: =(((INDEX('Category Assumptions'!$B$2:$B$6,MATCH(E$2,'Category Assumptions'!$A$2:$A$6,0))*(1-$A5))-INDEX('Category Assumptions'!$C$2:$C$6,MATCH(E$2,'Category Assumptions'!$A$2:$A$6,0)))*(INDEX('Category Assumptions'!$E$2:$E$6,MATCH(E$2,'Category Assumptions'!$A$2:$A$6,0))*(1+INDEX('Category Assumptions'!$F$2:$F$6,MATCH(E$2,'Category Assumptions'!$A$2:$A$6,0))*$A5))-((INDEX('Category Assumptions'!$B$2:$B$6,MATCH(E$2,'Category Assumptions'!$A$2:$A$6,0))-INDEX('Category Assumptions'!$C$2:$C$6,MATCH(E$2,'Category Assumptions'!$A$2:$A$6,0)))*INDEX('Category Assumptions'!$E$2:$E$6,MATCH(E$2,'Category Assumptions'!$A$2:$A$6,0))))/((INDEX('Category Assumptions'!$B$2:$B$6,MATCH(E$2,'Category Assumptions'!$A$2:$A$6,0))-INDEX('Category Assumptions'!$C$2:$C$6,MATCH(E$2,'Category Assumptions'!$A$2:$A$6,0)))*INDEX('Category Assumptions'!$E$2:$E$6,MATCH(E$2,'Category Assumptions'!$A$2:$A$6,0))) -> -0.063408029 | F5: =(((INDEX('Category Assumptions'!$B$2:$B$6,MATCH(F$2,'Category Assumptions'!$A$2:$A$6,0))*(1-$A5))-INDEX('Category Assumptions'!$C$2:$C$6,MATCH(F$2,'Category Assumptions'!$A$2:$A$6,0)))*(INDEX('Category Assumptions'!$E$2:$E$6,MATCH(F$2,'Category Assumptions'!$A$2:$A$6,0))*(1+INDEX('Category Assumptions'!$F$2:$F$6,MATCH(F$2,'Category Assumptions'!$A$2:$A$6,0))*$A5))-((INDEX('Category Assumptions'!$B$2:$B$6,MATCH(F$2,'Category Assumptions'!$A$2:$A$6,0))-INDEX('Category Assumptions'!$C$2:$C$6,MATCH(F$2,'Category Assumptions'!$A$2:$A$6,0)))*INDEX('Category Assumptions'!$E$2:$E$6,MATCH(F$2,'Category Assumptions'!$A$2:$A$6,0))))/((INDEX('Category Assumptions'!$B$2:$B$6,MATCH(F$2,'Category Assumptions'!$A$2:$A$6,0))-INDEX('Category Assumptions'!$C$2:$C$6,MATCH(F$2,'Category Assumptions'!$A$2:$A$6,0)))*INDEX('Category Assumptions'!$E$2:$E$6,MATCH(F$2,'Category Assumptions'!$A$2:$A$6,0))) -> -0.024875
A6: 0.15 | B6: =(((INDEX('Category Assumptions'!$B$2:$B$6,MATCH(B$2,'Category Assumptions'!$A$2:$A$6,0))*(1-$A6))-INDEX('Category Assumptions'!$C$2:$C$6,MATCH(B$2,'Category Assumptions'!$A$2:$A$6,0)))*(INDEX('Category Assumptions'!$E$2:$E$6,MATCH(B$2,'Category Assumptions'!$A$2:$A$6,0))*(1+INDEX('Category Assumptions'!$F$2:$F$6,MATCH(B$2,'Category Assumptions'!$A$2:$A$6,0))*$A6))-((INDEX('Category Assumptions'!$B$2:$B$6,MATCH(B$2,'Category Assumptions'!$A$2:$A$6,0))-INDEX('Category Assumptions'!$C$2:$C$6,MATCH(B$2,'Category Assumptions'!$A$2:$A$6,0)))*INDEX('Category Assumptions'!$E$2:$E$6,MATCH(B$2,'Category Assumptions'!$A$2:$A$6,0))))/((INDEX('Category Assumptions'!$B$2:$B$6,MATCH(B$2,'Category Assumptions'!$A$2:$A$6,0))-INDEX('Category Assumptions'!$C$2:$C$6,MATCH(B$2,'Category Assumptions'!$A$2:$A$6,0)))*INDEX('Category Assumptions'!$E$2:$E$6,MATCH(B$2,'Category Assumptions'!$A$2:$A$6,0))) -> -0.046922727 | C6: =(((INDEX('Category Assumptions'!$B$2:$B$6,MATCH(C$2,'Category Assumptions'!$A$2:$A$6,0))*(1-$A6))-INDEX('Category Assumptions'!$C$2:$C$6,MATCH(C$2,'Category Assumptions'!$A$2:$A$6,0)))*(INDEX('Category Assumptions'!$E$2:$E$6,MATCH(C$2,'Category Assumptions'!$A$2:$A$6,0))*(1+INDEX('Category Assumptions'!$F$2:$F$6,MATCH(C$2,'Category Assumptions'!$A$2:$A$6,0))*$A6))-((INDEX('Category Assumptions'!$B$2:$B$6,MATCH(C$2,'Category Assumptions'!$A$2:$A$6,0))-INDEX('Category Assumptions'!$C$2:$C$6,MATCH(C$2,'Category Assumptions'!$A$2:$A$6,0)))*INDEX('Category Assumptions'!$E$2:$E$6,MATCH(C$2,'Category Assumptions'!$A$2:$A$6,0))))/((INDEX('Category Assumptions'!$B$2:$B$6,MATCH(C$2,'Category Assumptions'!$A$2:$A$6,0))-INDEX('Category Assumptions'!$C$2:$C$6,MATCH(C$2,'Category Assumptions'!$A$2:$A$6,0)))*INDEX('Category Assumptions'!$E$2:$E$6,MATCH(C$2,'Category Assumptions'!$A$2:$A$6,0))) -> -0.0131875 | D6: =(((INDEX('Category Assumptions'!$B$2:$B$6,MATCH(D$2,'Category Assumptions'!$A$2:$A$6,0))*(1-$A6))-INDEX('Category Assumptions'!$C$2:$C$6,MATCH(D$2,'Category Assumptions'!$A$2:$A$6,0)))*(INDEX('Category Assumptions'!$E$2:$E$6,MATCH(D$2,'Category Assumptions'!$A$2:$A$6,0))*(1+INDEX('Category Assumptions'!$F$2:$F$6,MATCH(D$2,'Category Assumptions'!$A$2:$A$6,0))*$A6))-((INDEX('Category Assumptions'!$B$2:$B$6,MATCH(D$2,'Category Assumptions'!$A$2:$A$6,0))-INDEX('Category Assumptions'!$C$2:$C$6,MATCH(D$2,'Category Assumptions'!$A$2:$A$6,0)))*INDEX('Category Assumptions'!$E$2:$E$6,MATCH(D$2,'Category Assumptions'!$A$2:$A$6,0))))/((INDEX('Category Assumptions'!$B$2:$B$6,MATCH(D$2,'Category Assumptions'!$A$2:$A$6,0))-INDEX('Category Assumptions'!$C$2:$C$6,MATCH(D$2,'Category Assumptions'!$A$2:$A$6,0)))*INDEX('Category Assumptions'!$E$2:$E$6,MATCH(D$2,'Category Assumptions'!$A$2:$A$6,0))) -> -0.060833333 | E6: =(((INDEX('Category Assumptions'!$B$2:$B$6,MATCH(E$2,'Category Assumptions'!$A$2:$A$6,0))*(1-$A6))-INDEX('Category Assumptions'!$C$2:$C$6,MATCH(E$2,'Category Assumptions'!$A$2:$A$6,0)))*(INDEX('Category Assumptions'!$E$2:$E$6,MATCH(E$2,'Category Assumptions'!$A$2:$A$6,0))*(1+INDEX('Category Assumptions'!$F$2:$F$6,MATCH(E$2,'Category Assumptions'!$A$2:$A$6,0))*$A6))-((INDEX('Category Assumptions'!$B$2:$B$6,MATCH(E$2,'Category Assumptions'!$A$2:$A$6,0))-INDEX('Category Assumptions'!$C$2:$C$6,MATCH(E$2,'Category Assumptions'!$A$2:$A$6,0)))*INDEX('Category Assumptions'!$E$2:$E$6,MATCH(E$2,'Category Assumptions'!$A$2:$A$6,0))))/((INDEX('Category Assumptions'!$B$2:$B$6,MATCH(E$2,'Category Assumptions'!$A$2:$A$6,0))-INDEX('Category Assumptions'!$C$2:$C$6,MATCH(E$2,'Category Assumptions'!$A$2:$A$6,0)))*INDEX('Category Assumptions'!$E$2:$E$6,MATCH(E$2,'Category Assumptions'!$A$2:$A$6,0))) -> -0.1117999 | F6: =(((INDEX('Category Assumptions'!$B$2:$B$6,MATCH(F$2,'Category Assumptions'!$A$2:$A$6,0))*(1-$A6))-INDEX('Category Assumptions'!$C$2:$C$6,MATCH(F$2,'Category Assumptions'!$A$2:$A$6,0)))*(INDEX('Category Assumptions'!$E$2:$E$6,MATCH(F$2,'Category Assumptions'!$A$2:$A$6,0))*(1+INDEX('Category Assumptions'!$F$2:$F$6,MATCH(F$2,'Category Assumptions'!$A$2:$A$6,0))*$A6))-((INDEX('Category Assumptions'!$B$2:$B$6,MATCH(F$2,'Category Assumptions'!$A$2:$A$6,0))-INDEX('Category Assumptions'!$C$2:$C$6,MATCH(F$2,'Category Assumptions'!$A$2:$A$6,0)))*INDEX('Category Assumptions'!$E$2:$E$6,MATCH(F$2,'Category Assumptions'!$A$2:$A$6,0))))/((INDEX('Category Assumptions'!$B$2:$B$6,MATCH(F$2,'Category Assumptions'!$A$2:$A$6,0))-INDEX('Category Assumptions'!$C$2:$C$6,MATCH(F$2,'Category Assumptions'!$A$2:$A$6,0)))*INDEX('Category Assumptions'!$E$2:$E$6,MATCH(F$2,'Category Assumptions'!$A$2:$A$6,0))) -> -0.0564375
A7: 0.2 | B7: =(((INDEX('Category Assumptions'!$B$2:$B$6,MATCH(B$2,'Category Assumptions'!$A$2:$A$6,0))*(1-$A7))-INDEX('Category Assumptions'!$C$2:$C$6,MATCH(B$2,'Category Assumptions'!$A$2:$A$6,0)))*(INDEX('Category Assumptions'!$E$2:$E$6,MATCH(B$2,'Category Assumptions'!$A$2:$A$6,0))*(1+INDEX('Category Assumptions'!$F$2:$F$6,MATCH(B$2,'Category Assumptions'!$A$2:$A$6,0))*$A7))-((INDEX('Category Assumptions'!$B$2:$B$6,MATCH(B$2,'Category Assumptions'!$A$2:$A$6,0))-INDEX('Category Assumptions'!$C$2:$C$6,MATCH(B$2,'Category Assumptions'!$A$2:$A$6,0)))*INDEX('Category Assumptions'!$E$2:$E$6,MATCH(B$2,'Category Assumptions'!$A$2:$A$6,0))))/((INDEX('Category Assumptions'!$B$2:$B$6,MATCH(B$2,'Category Assumptions'!$A$2:$A$6,0))-INDEX('Category Assumptions'!$C$2:$C$6,MATCH(B$2,'Category Assumptions'!$A$2:$A$6,0)))*INDEX('Category Assumptions'!$E$2:$E$6,MATCH(B$2,'Category Assumptions'!$A$2:$A$6,0))) -> -0.092509091 | C7: =(((INDEX('Category Assumptions'!$B$2:$B$6,MATCH(C$2,'Category Assumptions'!$A$2:$A$6,0))*(1-$A7))-INDEX('Category Assumptions'!$C$2:$C$6,MATCH(C$2,'Category Assumptions'!$A$2:$A$6,0)))*(INDEX('Category Assumptions'!$E$2:$E$6,MATCH(C$2,'Category Assumptions'!$A$2:$A$6,0))*(1+INDEX('Category Assumptions'!$F$2:$F$6,MATCH(C$2,'Category Assumptions'!$A$2:$A$6,0))*$A7))-((INDEX('Category Assumptions'!$B$2:$B$6,MATCH(C$2,'Category Assumptions'!$A$2:$A$6,0))-INDEX('Category Assumptions'!$C$2:$C$6,MATCH(C$2,'Category Assumptions'!$A$2:$A$6,0)))*INDEX('Category Assumptions'!$E$2:$E$6,MATCH(C$2,'Category Assumptions'!$A$2:$A$6,0))))/((INDEX('Category Assumptions'!$B$2:$B$6,MATCH(C$2,'Category Assumptions'!$A$2:$A$6,0))-INDEX('Category Assumptions'!$C$2:$C$6,MATCH(C$2,'Category Assumptions'!$A$2:$A$6,0)))*INDEX('Category Assumptions'!$E$2:$E$6,MATCH(C$2,'Category Assumptions'!$A$2:$A$6,0))) -> -0.055428571 | D7: =(((INDEX('Category Assumptions'!$B$2:$B$6,MATCH(D$2,'Category Assumptions'!$A$2:$A$6,0))*(1-$A7))-INDEX('Category Assumptions'!$C$2:$C$6,MATCH(D$2,'Category Assumptions'!$A$2:$A$6,0)))*(INDEX('Category Assumptions'!$E$2:$E$6,MATCH(D$2,'Category Assumptions'!$A$2:$A$6,0))*(1+INDEX('Category Assumptions'!$F$2:$F$6,MATCH(D$2,'Category Assumptions'!$A$2:$A$6,0))*$A7))-((INDEX('Category Assumptions'!$B$2:$B$6,MATCH(D$2,'Category Assumptions'!$A$2:$A$6,0))-INDEX('Category Assumptions'!$C$2:$C$6,MATCH(D$2,'Category Assumptions'!$A$2:$A$6,0)))*INDEX('Category Assumptions'!$E$2:$E$6,MATCH(D$2,'Category Assumptions'!$A$2:$A$6,0))))/((INDEX('Category Assumptions'!$B$2:$B$6,MATCH(D$2,'Category Assumptions'!$A$2:$A$6,0))-INDEX('Category Assumptions'!$C$2:$C$6,MATCH(D$2,'Category Assumptions'!$A$2:$A$6,0)))*INDEX('Category Assumptions'!$E$2:$E$6,MATCH(D$2,'Category Assumptions'!$A$2:$A$6,0))) -> -0.10444444 | E7: =(((INDEX('Category Assumptions'!$B$2:$B$6,MATCH(E$2,'Category Assumptions'!$A$2:$A$6,0))*(1-$A7))-INDEX('Category Assumptions'!$C$2:$C$6,MATCH(E$2,'Category Assumptions'!$A$2:$A$6,0)))*(INDEX('Category Assumptions'!$E$2:$E$6,MATCH(E$2,'Category Assumptions'!$A$2:$A$6,0))*(1+INDEX('Category Assumptions'!$F$2:$F$6,MATCH(E$2,'Category Assumptions'!$A$2:$A$6,0))*$A7))-((INDEX('Category Assumptions'!$B$2:$B$6,MATCH(E$2,'Category Assumptions'!$A$2:$A$6,0))-INDEX('Category Assumptions'!$C$2:$C$6,MATCH(E$2,'Category Assumptions'!$A$2:$A$6,0)))*INDEX('Category Assumptions'!$E$2:$E$6,MATCH(E$2,'Category Assumptions'!$A$2:$A$6,0))))/((INDEX('Category Assumptions'!$B$2:$B$6,MATCH(E$2,'Category Assumptions'!$A$2:$A$6,0))-INDEX('Category Assumptions'!$C$2:$C$6,MATCH(E$2,'Category Assumptions'!$A$2:$A$6,0)))*INDEX('Category Assumptions'!$E$2:$E$6,MATCH(E$2,'Category Assumptions'!$A$2:$A$6,0))) -> -0.17131702 | F7: =(((INDEX('Category Assumptions'!$B$2:$B$6,MATCH(F$2,'Category Assumptions'!$A$2:$A$6,0))*(1-$A7))-INDEX('Category Assumptions'!$C$2:$C$6,MATCH(F$2,'Category Assumptions'!$A$2:$A$6,0)))*(INDEX('Category Assumptions'!$E$2:$E$6,MATCH(F$2,'Category Assumptions'!$A$2:$A$6,0))*(1+INDEX('Category Assumptions'!$F$2:$F$6,MATCH(F$2,'Category Assumptions'!$A$2:$A$6,0))*$A7))-((INDEX('Category Assumptions'!$B$2:$B$6,MATCH(F$2,'Category Assumptions'!$A$2:$A$6,0))-INDEX('Category Assumptions'!$C$2:$C$6,MATCH(F$2,'Category Assumptions'!$A$2:$A$6,0)))*INDEX('Category Assumptions'!$E$2:$E$6,MATCH(F$2,'Category Assumptions'!$A$2:$A$6,0))))/((INDEX('Category Assumptions'!$B$2:$B$6,MATCH(F$2,'Category Assumptions'!$A$2:$A$6,0))-INDEX('Category Assumptions'!$C$2:$C$6,MATCH(F$2,'Category Assumptions'!$A$2:$A$6,0)))*INDEX('Category Assumptions'!$E$2:$E$6,MATCH(F$2,'Category Assumptions'!$A$2:$A$6,0))) -> -0.10075
A8: 0.25 | B8: =(((INDEX('Category Assumptions'!$B$2:$B$6,MATCH(B$2,'Category Assumptions'!$A$2:$A$6,0))*(1-$A8))-INDEX('Category Assumptions'!$C$2:$C$6,MATCH(B$2,'Category Assumptions'!$A$2:$A$6,0)))*(INDEX('Category Assumptions'!$E$2:$E$6,MATCH(B$2,'Category Assumptions'!$A$2:$A$6,0))*(1+INDEX('Category Assumptions'!$F$2:$F$6,MATCH(B$2,'Category Assumptions'!$A$2:$A$6,0))*$A8))-((INDEX('Category Assumptions'!$B$2:$B$6,MATCH(B$2,'Category Assumptions'!$A$2:$A$6,0))-INDEX('Category Assumptions'!$C$2:$C$6,MATCH(B$2,'Category Assumptions'!$A$2:$A$6,0)))*INDEX('Category Assumptions'!$E$2:$E$6,MATCH(B$2,'Category Assumptions'!$A$2:$A$6,0))))/((INDEX('Category Assumptions'!$B$2:$B$6,MATCH(B$2,'Category Assumptions'!$A$2:$A$6,0))-INDEX('Category Assumptions'!$C$2:$C$6,MATCH(B$2,'Category Assumptions'!$A$2:$A$6,0)))*INDEX('Category Assumptions'!$E$2:$E$6,MATCH(B$2,'Category Assumptions'!$A$2:$A$6,0))) -> -0.15306818 | C8: =(((INDEX('Category Assumptions'!$B$2:$B$6,MATCH(C$2,'Category Assumptions'!$A$2:$A$6,0))*(1-$A8))-INDEX('Category Assumptions'!$C$2:$C$6,MATCH(C$2,'Category Assumptions'!$A$2:$A$6,0)))*(INDEX('Category Assumptions'!$E$2:$E$6,MATCH(C$2,'Category Assumptions'!$A$2:$A$6,0))*(1+INDEX('Category Assumptions'!$F$2:$F$6,MATCH(C$2,'Category Assumptions'!$A$2:$A$6,0))*$A8))-((INDEX('Category Assumptions'!$B$2:$B$6,MATCH(C$2,'Category Assumptions'!$A$2:$A$6,0))-INDEX('Category Assumptions'!$C$2:$C$6,MATCH(C$2,'Category Assumptions'!$A$2:$A$6,0)))*INDEX('Category Assumptions'!$E$2:$E$6,MATCH(C$2,'Category Assumptions'!$A$2:$A$6,0))))/((INDEX('Category Assumptions'!$B$2:$B$6,MATCH(C$2,'Category Assumptions'!$A$2:$A$6,0))-INDEX('Category Assumptions'!$C$2:$C$6,MATCH(C$2,'Category Assumptions'!$A$2:$A$6,0)))*INDEX('Category Assumptions'!$E$2:$E$6,MATCH(C$2,'Category Assumptions'!$A$2:$A$6,0))) -> -0.11659226 | D8: =(((INDEX('Category Assumptions'!$B$2:$B$6,MATCH(D$2,'Category Assumptions'!$A$2:$A$6,0))*(1-$A8))-INDEX('Category Assumptions'!$C$2:$C$6,MATCH(D$2,'Category Assumptions'!$A$2:$A$6,0)))*(INDEX('Category Assumptions'!$E$2:$E$6,MATCH(D$2,'Category Assumptions'!$A$2:$A$6,0))*(1+INDEX('Category Assumptions'!$F$2:$F$6,MATCH(D$2,'Category Assumptions'!$A$2:$A$6,0))*$A8))-((INDEX('Category Assumptions'!$B$2:$B$6,MATCH(D$2,'Category Assumptions'!$A$2:$A$6,0))-INDEX('Category Assumptions'!$C$2:$C$6,MATCH(D$2,'Category Assumptions'!$A$2:$A$6,0)))*INDEX('Category Assumptions'!$E$2:$E$6,MATCH(D$2,'Category Assumptions'!$A$2:$A$6,0))))/((INDEX('Category Assumptions'!$B$2:$B$6,MATCH(D$2,'Category Assumptions'!$A$2:$A$6,0))-INDEX('Category Assumptions'!$C$2:$C$6,MATCH(D$2,'Category Assumptions'!$A$2:$A$6,0)))*INDEX('Category Assumptions'!$E$2:$E$6,MATCH(D$2,'Category Assumptions'!$A$2:$A$6,0))) -> -0.15972222 | E8: =(((INDEX('Category Assumptions'!$B$2:$B$6,MATCH(E$2,'Category Assumptions'!$A$2:$A$6,0))*(1-$A8))-INDEX('Category Assumptions'!$C$2:$C$6,MATCH(E$2,'Category Assumptions'!$A$2:$A$6,0)))*(INDEX('Category Assumptions'!$E$2:$E$6,MATCH(E$2,'Category Assumptions'!$A$2:$A$6,0))*(1+INDEX('Category Assumptions'!$F$2:$F$6,MATCH(E$2,'Category Assumptions'!$A$2:$A$6,0))*$A8))-((INDEX('Category Assumptions'!$B$2:$B$6,MATCH(E$2,'Category Assumptions'!$A$2:$A$6,0))-INDEX('Category Assumptions'!$C$2:$C$6,MATCH(E$2,'Category Assumptions'!$A$2:$A$6,0)))*INDEX('Category Assumptions'!$E$2:$E$6,MATCH(E$2,'Category Assumptions'!$A$2:$A$6,0))))/((INDEX('Category Assumptions'!$B$2:$B$6,MATCH(E$2,'Category Assumptions'!$A$2:$A$6,0))-INDEX('Category Assumptions'!$C$2:$C$6,MATCH(E$2,'Category Assumptions'!$A$2:$A$6,0)))*INDEX('Category Assumptions'!$E$2:$E$6,MATCH(E$2,'Category Assumptions'!$A$2:$A$6,0))) -> -0.24195938 | F8: =(((INDEX('Category Assumptions'!$B$2:$B$6,MATCH(F$2,'Category Assumptions'!$A$2:$A$6,0))*(1-$A8))-INDEX('Category Assumptions'!$C$2:$C$6,MATCH(F$2,'Category Assumptions'!$A$2:$A$6,0)))*(INDEX('Category Assumptions'!$E$2:$E$6,MATCH(F$2,'Category Assumptions'!$A$2:$A$6,0))*(1+INDEX('Category Assumptions'!$F$2:$F$6,MATCH(F$2,'Category Assumptions'!$A$2:$A$6,0))*$A8))-((INDEX('Category Assumptions'!$B$2:$B$6,MATCH(F$2,'Category Assumptions'!$A$2:$A$6,0))-INDEX('Category Assumptions'!$C$2:$C$6,MATCH(F$2,'Category Assumptions'!$A$2:$A$6,0)))*INDEX('Category Assumptions'!$E$2:$E$6,MATCH(F$2,'Category Assumptions'!$A$2:$A$6,0))))/((INDEX('Category Assumptions'!$B$2:$B$6,MATCH(F$2,'Category Assumptions'!$A$2:$A$6,0))-INDEX('Category Assumptions'!$C$2:$C$6,MATCH(F$2,'Category Assumptions'!$A$2:$A$6,0)))*INDEX('Category Assumptions'!$E$2:$E$6,MATCH(F$2,'Category Assumptions'!$A$2:$A$6,0))) -> -0.1578125
A9: 0.3 | B9: =(((INDEX('Category Assumptions'!$B$2:$B$6,MATCH(B$2,'Category Assumptions'!$A$2:$A$6,0))*(1-$A9))-INDEX('Category Assumptions'!$C$2:$C$6,MATCH(B$2,'Category Assumptions'!$A$2:$A$6,0)))*(INDEX('Category Assumptions'!$E$2:$E$6,MATCH(B$2,'Category Assumptions'!$A$2:$A$6,0))*(1+INDEX('Category Assumptions'!$F$2:$F$6,MATCH(B$2,'Category Assumptions'!$A$2:$A$6,0))*$A9))-((INDEX('Category Assumptions'!$B$2:$B$6,MATCH(B$2,'Category Assumptions'!$A$2:$A$6,0))-INDEX('Category Assumptions'!$C$2:$C$6,MATCH(B$2,'Category Assumptions'!$A$2:$A$6,0)))*INDEX('Category Assumptions'!$E$2:$E$6,MATCH(B$2,'Category Assumptions'!$A$2:$A$6,0))))/((INDEX('Category Assumptions'!$B$2:$B$6,MATCH(B$2,'Category Assumptions'!$A$2:$A$6,0))-INDEX('Category Assumptions'!$C$2:$C$6,MATCH(B$2,'Category Assumptions'!$A$2:$A$6,0)))*INDEX('Category Assumptions'!$E$2:$E$6,MATCH(B$2,'Category Assumptions'!$A$2:$A$6,0))) -> -0.2286 | C9: =(((INDEX('Category Assumptions'!$B$2:$B$6,MATCH(C$2,'Category Assumptions'!$A$2:$A$6,0))*(1-$A9))-INDEX('Category Assumptions'!$C$2:$C$6,MATCH(C$2,'Category Assumptions'!$A$2:$A$6,0)))*(INDEX('Category Assumptions'!$E$2:$E$6,MATCH(C$2,'Category Assumptions'!$A$2:$A$6,0))*(1+INDEX('Category Assumptions'!$F$2:$F$6,MATCH(C$2,'Category Assumptions'!$A$2:$A$6,0))*$A9))-((INDEX('Category Assumptions'!$B$2:$B$6,MATCH(C$2,'Category Assumptions'!$A$2:$A$6,0))-INDEX('Category Assumptions'!$C$2:$C$6,MATCH(C$2,'Category Assumptions'!$A$2:$A$6,0)))*INDEX('Category Assumptions'!$E$2:$E$6,MATCH(C$2,'Category Assumptions'!$A$2:$A$6,0))))/((INDEX('Category Assumptions'!$B$2:$B$6,MATCH(C$2,'Category Assumptions'!$A$2:$A$6,0))-INDEX('Category Assumptions'!$C$2:$C$6,MATCH(C$2,'Category Assumptions'!$A$2:$A$6,0)))*INDEX('Category Assumptions'!$E$2:$E$6,MATCH(C$2,'Category Assumptions'!$A$2:$A$6,0))) -> -0.19667857 | D9: =(((INDEX('Category Assumptions'!$B$2:$B$6,MATCH(D$2,'Category Assumptions'!$A$2:$A$6,0))*(1-$A9))-INDEX('Category Assumptions'!$C$2:$C$6,MATCH(D$2,'Category Assumptions'!$A$2:$A$6,0)))*(INDEX('Category Assumptions'!$E$2:$E$6,MATCH(D$2,'Category Assumptions'!$A$2:$A$6,0))*(1+INDEX('Category Assumptions'!$F$2:$F$6,MATCH(D$2,'Category Assumptions'!$A$2:$A$6,0))*$A9))-((INDEX('Category Assumptions'!$B$2:$B$6,MATCH(D$2,'Category Assumptions'!$A$2:$A$6,0))-INDEX('Category Assumptions'!$C$2:$C$6,MATCH(D$2,'Category Assumptions'!$A$2:$A$6,0)))*INDEX('Category Assumptions'!$E$2:$E$6,MATCH(D$2,'Category Assumptions'!$A$2:$A$6,0))))/((INDEX('Category Assumptions'!$B$2:$B$6,MATCH(D$2,'Category Assumptions'!$A$2:$A$6,0))-INDEX('Category Assumptions'!$C$2:$C$6,MATCH(D$2,'Category Assumptions'!$A$2:$A$6,0)))*INDEX('Category Assumptions'!$E$2:$E$6,MATCH(D$2,'Category Assumptions'!$A$2:$A$6,0))) -> -0.22666667 | E9: =(((INDEX('Category Assumptions'!$B$2:$B$6,MATCH(E$2,'Category Assumptions'!$A$2:$A$6,0))*(1-$A9))-INDEX('Category Assumptions'!$C$2:$C$6,MATCH(E$2,'Category Assumptions'!$A$2:$A$6,0)))*(INDEX('Category Assumptions'!$E$2:$E$6,MATCH(E$2,'Category Assumptions'!$A$2:$A$6,0))*(1+INDEX('Category Assumptions'!$F$2:$F$6,MATCH(E$2,'Category Assumptions'!$A$2:$A$6,0))*$A9))-((INDEX('Category Assumptions'!$B$2:$B$6,MATCH(E$2,'Category Assumptions'!$A$2:$A$6,0))-INDEX('Category Assumptions'!$C$2:$C$6,MATCH(E$2,'Category Assumptions'!$A$2:$A$6,0)))*INDEX('Category Assumptions'!$E$2:$E$6,MATCH(E$2,'Category Assumptions'!$A$2:$A$6,0))))/((INDEX('Category Assumptions'!$B$2:$B$6,MATCH(E$2,'Category Assumptions'!$A$2:$A$6,0))-INDEX('Category Assumptions'!$C$2:$C$6,MATCH(E$2,'Category Assumptions'!$A$2:$A$6,0)))*INDEX('Category Assumptions'!$E$2:$E$6,MATCH(E$2,'Category Assumptions'!$A$2:$A$6,0))) -> -0.32372697 | F9: =(((INDEX('Category Assumptions'!$B$2:$B$6,MATCH(F$2,'Category Assumptions'!$A$2:$A$6,0))*(1-$A9))-INDEX('Category Assumptions'!$C$2:$C$6,MATCH(F$2,'Category Assumptions'!$A$2:$A$6,0)))*(INDEX('Category Assumptions'!$E$2:$E$6,MATCH(F$2,'Category Assumptions'!$A$2:$A$6,0))*(1+INDEX('Category Assumptions'!$F$2:$F$6,MATCH(F$2,'Category Assumptions'!$A$2:$A$6,0))*$A9))-((INDEX('Category Assumptions'!$B$2:$B$6,MATCH(F$2,'Category Assumptions'!$A$2:$A$6,0))-INDEX('Category Assumptions'!$C$2:$C$6,MATCH(F$2,'Category Assumptions'!$A$2:$A$6,0)))*INDEX('Category Assumptions'!$E$2:$E$6,MATCH(F$2,'Category Assumptions'!$A$2:$A$6,0))))/((INDEX('Category Assumptions'!$B$2:$B$6,MATCH(F$2,'Category Assumptions'!$A$2:$A$6,0))-INDEX('Category Assumptions'!$C$2:$C$6,MATCH(F$2,'Category Assumptions'!$A$2:$A$6,0)))*INDEX('Category Assumptions'!$E$2:$E$6,MATCH(F$2,'Category Assumptions'!$A$2:$A$6,0))) -> -0.227625
A10: 0.35 | B10: =(((INDEX('Category Assumptions'!$B$2:$B$6,MATCH(B$2,'Category Assumptions'!$A$2:$A$6,0))*(1-$A10))-INDEX('Category Assumptions'!$C$2:$C$6,MATCH(B$2,'Category Assumptions'!$A$2:$A$6,0)))*(INDEX('Category Assumptions'!$E$2:$E$6,MATCH(B$2,'Category Assumptions'!$A$2:$A$6,0))*(1+INDEX('Category Assumptions'!$F$2:$F$6,MATCH(B$2,'Category Assumptions'!$A$2:$A$6,0))*$A10))-((INDEX('Category Assumptions'!$B$2:$B$6,MATCH(B$2,'Category Assumptions'!$A$2:$A$6,0))-INDEX('Category Assumptions'!$C$2:$C$6,MATCH(B$2,'Category Assumptions'!$A$2:$A$6,0)))*INDEX('Category Assumptions'!$E$2:$E$6,MATCH(B$2,'Category Assumptions'!$A$2:$A$6,0))))/((INDEX('Category Assumptions'!$B$2:$B$6,MATCH(B$2,'Category Assumptions'!$A$2:$A$6,0))-INDEX('Category Assumptions'!$C$2:$C$6,MATCH(B$2,'Category Assumptions'!$A$2:$A$6,0)))*INDEX('Category Assumptions'!$E$2:$E$6,MATCH(B$2,'Category Assumptions'!$A$2:$A$6,0))) -> -0.31910455 | C10: =(((INDEX('Category Assumptions'!$B$2:$B$6,MATCH(C$2,'Category Assumptions'!$A$2:$A$6,0))*(1-$A10))-INDEX('Category Assumptions'!$C$2:$C$6,MATCH(C$2,'Category Assumptions'!$A$2:$A$6,0)))*(INDEX('Category Assumptions'!$E$2:$E$6,MATCH(C$2,'Category Assumptions'!$A$2:$A$6,0))*(1+INDEX('Category Assumptions'!$F$2:$F$6,MATCH(C$2,'Category Assumptions'!$A$2:$A$6,0))*$A10))-((INDEX('Category Assumptions'!$B$2:$B$6,MATCH(C$2,'Category Assumptions'!$A$2:$A$6,0))-INDEX('Category Assumptions'!$C$2:$C$6,MATCH(C$2,'Category Assumptions'!$A$2:$A$6,0)))*INDEX('Category Assumptions'!$E$2:$E$6,MATCH(C$2,'Category Assumptions'!$A$2:$A$6,0))))/((INDEX('Category Assumptions'!$B$2:$B$6,MATCH(C$2,'Category Assumptions'!$A$2:$A$6,0))-INDEX('Category Assumptions'!$C$2:$C$6,MATCH(C$2,'Category Assumptions'!$A$2:$A$6,0)))*INDEX('Category Assumptions'!$E$2:$E$6,MATCH(C$2,'Category Assumptions'!$A$2:$A$6,0))) -> -0.2956875 | D10: =(((INDEX('Category Assumptions'!$B$2:$B$6,MATCH(D$2,'Category Assumptions'!$A$2:$A$6,0))*(1-$A10))-INDEX('Category Assumptions'!$C$2:$C$6,MATCH(D$2,'Category Assumptions'!$A$2:$A$6,0)))*(INDEX('Category Assumptions'!$E$2:$E$6,MATCH(D$2,'Category Assumptions'!$A$2:$A$6,0))*(1+INDEX('Category Assumptions'!$F$2:$F$6,MATCH(D$2,'Category Assumptions'!$A$2:$A$6,0))*$A10))-((INDEX('Category Assumptions'!$B$2:$B$6,MATCH(D$2,'Category Assumptions'!$A$2:$A$6,0))-INDEX('Category Assumptions'!$C$2:$C$6,MATCH(D$2,'Category Assumptions'!$A$2:$A$6,0)))*INDEX('Category Assumptions'!$E$2:$E$6,MATCH(D$2,'Category Assumptions'!$A$2:$A$6,0))))/((INDEX('Category Assumptions'!$B$2:$B$6,MATCH(D$2,'Category Assumptions'!$A$2:$A$6,0))-INDEX('Category Assumptions'!$C$2:$C$6,MATCH(D$2,'Category Assumptions'!$A$2:$A$6,0)))*INDEX('Category Assumptions'!$E$2:$E$6,MATCH(D$2,'Category Assumptions'!$A$2:$A$6,0))) -> -0.30527778 | E10: =(((INDEX('Category Assumptions'!$B$2:$B$6,MATCH(E$2,'Category Assumptions'!$A$2:$A$6,0))*(1-$A10))-INDEX('Category Assumptions'!$C$2:$C$6,MATCH(E$2,'Category Assumptions'!$A$2:$A$6,0)))*(INDEX('Category Assumptions'!$E$2:$E$6,MATCH(E$2,'Category Assumptions'!$A$2:$A$6,0))*(1+INDEX('Category Assumptions'!$F$2:$F$6,MATCH(E$2,'Category Assumptions'!$A$2:$A$6,0))*$A10))-((INDEX('Category Assumptions'!$B$2:$B$6,MATCH(E$2,'Category Assumptions'!$A$2:$A$6,0))-INDEX('Category Assumptions'!$C$2:$C$6,MATCH(E$2,'Category Assumptions'!$A$2:$A$6,0)))*INDEX('Category Assumptions'!$E$2:$E$6,MATCH(E$2,'Category Assumptions'!$A$2:$A$6,0))))/((INDEX('Category Assumptions'!$B$2:$B$6,MATCH(E$2,'Category Assumptions'!$A$2:$A$6,0))-INDEX('Category Assumptions'!$C$2:$C$6,MATCH(E$2,'Category Assumptions'!$A$2:$A$6,0)))*INDEX('Category Assumptions'!$E$2:$E$6,MATCH(E$2,'Category Assumptions'!$A$2:$A$6,0))) -> -0.41661981 | F10: =(((INDEX('Category Assumptions'!$B$2:$B$6,MATCH(F$2,'Category Assumptions'!$A$2:$A$6,0))*(1-$A10))-INDEX('Category Assumptions'!$C$2:$C$6,MATCH(F$2,'Category Assumptions'!$A$2:$A$6,0)))*(INDEX('Category Assumptions'!$E$2:$E$6,MATCH(F$2,'Category Assumptions'!$A$2:$A$6,0))*(1+INDEX('Category Assumptions'!$F$2:$F$6,MATCH(F$2,'Category Assumptions'!$A$2:$A$6,0))*$A10))-((INDEX('Category Assumptions'!$B$2:$B$6,MATCH(F$2,'Category Assumptions'!$A$2:$A$6,0))-INDEX('Category Assumptions'!$C$2:$C$6,MATCH(F$2,'Category Assumptions'!$A$2:$A$6,0)))*INDEX('Category Assumptions'!$E$2:$E$6,MATCH(F$2,'Category Assumptions'!$A$2:$A$6,0))))/((INDEX('Category Assumptions'!$B$2:$B$6,MATCH(F$2,'Category Assumptions'!$A$2:$A$6,0))-INDEX('Category Assumptions'!$C$2:$C$6,MATCH(F$2,'Category Assumptions'!$A$2:$A$6,0)))*INDEX('Category Assumptions'!$E$2:$E$6,MATCH(F$2,'Category Assumptions'!$A$2:$A$6,0))) -> -0.3101875
A11: 0.4 | B11: =(((INDEX('Category Assumptions'!$B$2:$B$6,MATCH(B$2,'Category Assumptions'!$A$2:$A$6,0))*(1-$A11))-INDEX('Category Assumptions'!$C$2:$C$6,MATCH(B$2,'Category Assumptions'!$A$2:$A$6,0)))*(INDEX('Category Assumptions'!$E$2:$E$6,MATCH(B$2,'Category Assumptions'!$A$2:$A$6,0))*(1+INDEX('Category Assumptions'!$F$2:$F$6,MATCH(B$2,'Category Assumptions'!$A$2:$A$6,0))*$A11))-((INDEX('Category Assumptions'!$B$2:$B$6,MATCH(B$2,'Category Assumptions'!$A$2:$A$6,0))-INDEX('Category Assumptions'!$C$2:$C$6,MATCH(B$2,'Category Assumptions'!$A$2:$A$6,0)))*INDEX('Category Assumptions'!$E$2:$E$6,MATCH(B$2,'Category Assumptions'!$A$2:$A$6,0))))/((INDEX('Category Assumptions'!$B$2:$B$6,MATCH(B$2,'Category Assumptions'!$A$2:$A$6,0))-INDEX('Category Assumptions'!$C$2:$C$6,MATCH(B$2,'Category Assumptions'!$A$2:$A$6,0)))*INDEX('Category Assumptions'!$E$2:$E$6,MATCH(B$2,'Category Assumptions'!$A$2:$A$6,0))) -> -0.42458182 | C11: =(((INDEX('Category Assumptions'!$B$2:$B$6,MATCH(C$2,'Category Assumptions'!$A$2:$A$6,0))*(1-$A11))-INDEX('Category Assumptions'!$C$2:$C$6,MATCH(C$2,'Category Assumptions'!$A$2:$A$6,0)))*(INDEX('Category Assumptions'!$E$2:$E$6,MATCH(C$2,'Category Assumptions'!$A$2:$A$6,0))*(1+INDEX('Category Assumptions'!$F$2:$F$6,MATCH(C$2,'Category Assumptions'!$A$2:$A$6,0))*$A11))-((INDEX('Category Assumptions'!$B$2:$B$6,MATCH(C$2,'Category Assumptions'!$A$2:$A$6,0))-INDEX('Category Assumptions'!$C$2:$C$6,MATCH(C$2,'Category Assumptions'!$A$2:$A$6,0)))*INDEX('Category Assumptions'!$E$2:$E$6,MATCH(C$2,'Category Assumptions'!$A$2:$A$6,0))))/((INDEX('Category Assumptions'!$B$2:$B$6,MATCH(C$2,'Category Assumptions'!$A$2:$A$6,0))-INDEX('Category Assumptions'!$C$2:$C$6,MATCH(C$2,'Category Assumptions'!$A$2:$A$6,0)))*INDEX('Category Assumptions'!$E$2:$E$6,MATCH(C$2,'Category Assumptions'!$A$2:$A$6,0))) -> -0.41361905 | D11: =(((INDEX('Category Assumptions'!$B$2:$B$6,MATCH(D$2,'Category Assumptions'!$A$2:$A$6,0))*(1-$A11))-INDEX('Category Assumptions'!$C$2:$C$6,MATCH(D$2,'Category Assumptions'!$A$2:$A$6,0)))*(INDEX('Category Assumptions'!$E$2:$E$6,MATCH(D$2,'Category Assumptions'!$A$2:$A$6,0))*(1+INDEX('Category Assumptions'!$F$2:$F$6,MATCH(D$2,'Category Assumptions'!$A$2:$A$6,0))*$A11))-((INDEX('Category Assumptions'!$B$2:$B$6,MATCH(D$2,'Category Assumptions'!$A$2:$A$6,0))-INDEX('Category Assumptions'!$C$2:$C$6,MATCH(D$2,'Category Assumptions'!$A$2:$A$6,0)))*INDEX('Category Assumptions'!$E$2:$E$6,MATCH(D$2,'Category Assumptions'!$A$2:$A$6,0))))/((INDEX('Category Assumptions'!$B$2:$B$6,MATCH(D$2,'Category Assumptions'!$A$2:$A$6,0))-INDEX('Category Assumptions'!$C$2:$C$6,MATCH(D$2,'Category Assumptions'!$A$2:$A$6,0)))*INDEX('Category Assumptions'!$E$2:$E$6,MATCH(D$2,'Category Assumptions'!$A$2:$A$6,0))) -> -0.39555556 | E11: =(((INDEX('Category Assumptions'!$B$2:$B$6,MATCH(E$2,'Category Assumptions'!$A$2:$A$6,0))*(1-$A11))-INDEX('Category Assumptions'!$C$2:$C$6,MATCH(E$2,'Category Assumptions'!$A$2:$A$6,0)))*(INDEX('Category Assumptions'!$E$2:$E$6,MATCH(E$2,'Category Assumptions'!$A$2:$A$6,0))*(1+INDEX('Category Assumptions'!$F$2:$F$6,MATCH(E$2,'Category Assumptions'!$A$2:$A$6,0))*$A11))-((INDEX('Category Assumptions'!$B$2:$B$6,MATCH(E$2,'Category Assumptions'!$A$2:$A$6,0))-INDEX('Category Assumptions'!$C$2:$C$6,MATCH(E$2,'Category Assumptions'!$A$2:$A$6,0)))*INDEX('Category Assumptions'!$E$2:$E$6,MATCH(E$2,'Category Assumptions'!$A$2:$A$6,0))))/((INDEX('Category Assumptions'!$B$2:$B$6,MATCH(E$2,'Category Assumptions'!$A$2:$A$6,0))-INDEX('Category Assumptions'!$C$2:$C$6,MATCH(E$2,'Category Assumptions'!$A$2:$A$6,0)))*INDEX('Category Assumptions'!$E$2:$E$6,MATCH(E$2,'Category Assumptions'!$A$2:$A$6,0))) -> -0.52063789 | F11: =(((INDEX('Category Assumptions'!$B$2:$B$6,MATCH(F$2,'Category Assumptions'!$A$2:$A$6,0))*(1-$A11))-INDEX('Category Assumptions'!$C$2:$C$6,MATCH(F$2,'Category Assumptions'!$A$2:$A$6,0)))*(INDEX('Category Assumptions'!$E$2:$E$6,MATCH(F$2,'Category Assumptions'!$A$2:$A$6,0))*(1+INDEX('Category Assumptions'!$F$2:$F$6,MATCH(F$2,'Category Assumptions'!$A$2:$A$6,0))*$A11))-((INDEX('Category Assumptions'!$B$2:$B$6,MATCH(F$2,'Category Assumptions'!$A$2:$A$6,0))-INDEX('Category Assumptions'!$C$2:$C$6,MATCH(F$2,'Category Assumptions'!$A$2:$A$6,0)))*INDEX('Category Assumptions'!$E$2:$E$6,MATCH(F$2,'Category Assumptions'!$A$2:$A$6,0))))/((INDEX('Category Assumptions'!$B$2:$B$6,MATCH(F$2,'Category Assumptions'!$A$2:$A$6,0))-INDEX('Category Assumptions'!$C$2:$C$6,MATCH(F$2,'Category Assumptions'!$A$2:$A$6,0)))*INDEX('Category Assumptions'!$E$2:$E$6,MATCH(F$2,'Category Assumptions'!$A$2:$A$6,0))) -> -0.4055

Sheet Scenario Comparison
A1: Scenario Comparison — for the category currently selected on Markdown Model
A2: Scenario | B2: Discount % | C2: New Price | D2: New Volume | E2: Revenue | F2: Profit | G2: Profit Change %
A3: No Discount | B3: =0 -> 0 | C3: ='Markdown Model'!$C$9*(1-B3) -> 45.75 | D3: ='Markdown Model'!$C$11*(1+'Markdown Model'!$C$12*B3) -> 380 | E3: =C3*D3 -> 17385 | F3: =(C3-'Markdown Model'!$C$10)*D3 -> 10450 | G3: =(F3-'Markdown Model'!$C$17)/'Markdown Model'!$C$17 -> 0
A4: Light Promo | B4: =0.1 -> 0.1 | C4: ='Markdown Model'!$C$9*(1-B4) -> 41.175 | D4: ='Markdown Model'!$C$11*(1+'Markdown Model'!$C$12*B4) -> 448.4 | E4: =C4*D4 -> 18462.87 | F4: =(C4-'Markdown Model'!$C$10)*D4 -> 10279.57 | G4: =(F4-'Markdown Model'!$C$17)/'Markdown Model'!$C$17 -> -0.016309091
A5: Moderate Promo | B5: =0.2 -> 0.2 | C5: ='Markdown Model'!$C$9*(1-B5) -> 36.6 | D5: ='Markdown Model'!$C$11*(1+'Markdown Model'!$C$12*B5) -> 516.8 | E5: =C5*D5 -> 18914.88 | F5: =(C5-'Markdown Model'!$C$10)*D5 -> 9483.28 | G5: =(F5-'Markdown Model'!$C$17)/'Markdown Model'!$C$17 -> -0.092509091
A6: Deep Clearance | B6: =0.3 -> 0.3 | C6: ='Markdown Model'!$C$9*(1-B6) -> 32.025 | D6: ='Markdown Model'!$C$11*(1+'Markdown Model'!$C$12*B6) -> 585.2 | E6: =C6*D6 -> 18741.03 | F6: =(C6-'Markdown Model'!$C$10)*D6 -> 8061.13 | G6: =(F6-'Markdown Model'!$C$17)/'Markdown Model'!$C$17 -> -0.2286
A7: Custom (Markdown Model) | B7: ='Markdown Model'!$C$6 -> 0.2 | C7: ='Markdown Model'!$C$9*(1-B7) -> 36.6 | D7: ='Markdown Model'!$C$11*(1+'Markdown Model'!$C$12*B7) -> 516.8 | E7: =C7*D7 -> 18914.88 | F7: =(C7-'Markdown Model'!$C$10)*D7 -> 9483.28 | G7: =(F7-'Markdown Model'!$C$17)/'Markdown Model'!$C$17 -> -0.092509091
