Workbook

Sheet README
B2: Inventory ABC Analysis & Reorder Point Model
B4: Business Problem
B5: The warehouse is overstocked on low-value SKUs and stocking out on high-value ones, because every SKU is managed with the same review cadence and safety stock rule. Not all 20 SKUs deserve equal attention — a small number drive most of the inventory value and need tighter control, while the rest can run leaner.
B7: Excel Skills Demonstrated
B8: • SUMPRODUCT for a sort-free running-total (cumulative value) calculation
B9: • RANK to order SKUs by annual usage value without physically re-sorting the table
B10: • Nested IF classification into A / B / C tiers based on cumulative revenue share
B11: • Differentiated safety-stock formulas by tier (tighter service level for A-items)
B12: • Reorder point and EOQ (Economic Order Quantity) formulas
B13: • Conditional formatting to flag class and reorder urgency at a glance
B14: • Pareto-style chart (bar + cumulative % line) on the dashboard
B16: The ABC Method
... B34: Source: synthetic SKU data generated for this project (see gen_sku_data.py). Unit costs/prices are shared with the 01-sales-dashboard project for portfolio continuity; demand, lead time, and cost assumptions are illustrative, not real.

Sheet Dashboard
B2: Inventory ABC Analysis & Reorder Point Dashboard
B3: 20 SKUs | 5 Categories | Annual Usage Value Basis
B5: Total Annual Usage Value | D5: Class A SKUs | F5: Class A Share of Value | H5: Avg Reorder Point (units)
B6: =SUM('ABC Analysis'!D2:D21) -> 276997 | D6: ='ABC Analysis'!B26 -> 8 | F6: ='ABC Analysis'!E26 -> 0 | H6: =AVERAGE('Reorder Point Model'!I2:I21) -> 54.609942
B9: Top Value SKU | F9: Highest Reorder Point SKU (watch closely)
B10: =INDEX('ABC Analysis'!B2:B21,MATCH(1,'ABC Analysis'!E2:E21,0)) -> Fitness Tracker Band | F10: =INDEX('Reorder Point Model'!B2:B21,MATCH(MAX('Reorder Point Model'!I2:I21),'Reorder Point Model'!I2:I21,0)) -> Fitness Tracker Band

Sheet SKU Data
A1: SKU | B1: Product | C1: Category | D1: Unit Cost | E1: Unit Price | F1: Annual Units Sold | G1: Avg Daily Demand | H1: Demand Std Dev | I1: Lead Time (days) | J1: Order Cost | K1: Holding Cost %
A2: ELE-403 | B2: Fitness Tracker Band | C2: Electronics | D2: 42 | E2: 99 | F2: 1845 | G2: 5.05 | H2: 1.31 | I2: 45 | J2: 79.1 | K2: 0.23
A3: FTW-201 | B3: Running Sneakers | C3: Footwear | D3: 38 | E3: 89 | F3: 821 | G3: 2.25 | H3: 0.77 | I3: 14 | J3: 99.48 | K3: 0.22
A4: ACC-302 | B4: Aviator Sunglasses | C4: Accessories | D4: 15 | E4: 42 | F4: 1533 | G4: 4.2 | H4: 1.43 | I4: 10 | J4: 52.99 | K4: 0.2
A5: FTW-202 | B5: Canvas Low-Top | C5: Footwear | D5: 22 | E5: 55 | F5: 949 | G5: 2.6 | H5: 0.73 | I5: 14 | J5: 80.96 | K5: 0.22
A6: ELE-401 | B6: Wireless Earbuds | C6: Electronics | D6: 34 | E6: 79 | F6: 575 | G6: 1.58 | H6: 0.79 | I6: 21 | J6: 92.15 | K6: 0.24
A7: FTW-203 | B7: Leather Ankle Boot | C7: Footwear | D7: 52 | E7: 120 | F7: 313 | G7: 0.86 | H7: 0.38 | I7: 45 | J7: 114.84 | K7: 0.21
A8: HOM-503 | B8: Cotton Throw Blanket | C8: Home Goods | D8: 15 | E8: 38 | F8: 1024 | G8: 2.81 | H8: 1.52 | I8: 14 | J8: 49.13 | K8: 0.17
A9: ELE-402 | B9: Bluetooth Speaker | C9: Electronics | D9: 24 | E9: 59 | F9: 571 | G9: 1.56 | H9: 0.69 | I9: 45 | J9: 71.31 | K9: 0.2
A10: APP-101 | B10: Classic Denim Jacket | C10: Apparel | D10: 27.5 | E10: 68 | F10: 334 | G10: 0.92 | H10: 0.34 | I10: 7 | J10: 47.97 | K10: 0.22
A11: APP-103 | B11: Fleece Pullover Hoodie | C11: Apparel | D11: 18 | E11: 45 | F11: 426 | G11: 1.17 | H11: 0.33 | I11: 30 | J11: 46.5 | K11: 0.22
A12: FTW-204 | B12: Slide Sandals | C12: Footwear | D12: 9 | E12: 25 | F12: 852 | G12: 2.33 | H12: 1 | I12: 45 | J12: 79.77 | K12: 0.18
A13: HOM-504 | B13: Bamboo Cutting Board | C13: Home Goods | D13: 10 | E13: 27 | F13: 752 | G13: 2.06 | H13: 0.52 | I13: 14 | J13: 68.9 | K13: 0.15
... A21: APP-102 | B21: Cotton Crew T-Shirt | C21: Apparel | D21: 6.5 | E21: 18 | F21: 239 | G21: 0.65 | H21: 0.34 | I21: 14 | J21: 44.12 | K21: 0.21

Sheet Assumptions
A1: Inventory Optimization Assumptions
A3: ABC Classification | D3: Service Levels | G3: Z Scores
A4: Class A Threshold | B4: 0.8 | D4: Class A | E4: 0.99 | G4: Class A | H4: 2.33
A5: Class B Threshold | B5: 0.95 | D5: Class B | E5: 0.95 | G5: Class B | H5: 1.65
A6: Class C Threshold | B6: 1 | D6: Class C | E6: 0.9 | G6: Class A | H6: 1.28
A9: XYZ Classification
A10: X up to | B10: 0.5
A11: Y up to | B11: 1
A12: z = remainder

Sheet ABC Analysis
A1: SKU | B1: Product | C1: Category | D1: Annual Usage Value | E1: Rank | F1: Cumulative Value | G1: Cumulative % | H1: Class
A2: ='SKU Data'!A2 -> ELE-403 | B2: ='SKU Data'!B2 -> Fitness Tracker Band | C2: ='SKU Data'!C2 -> Electronics | D2: ='SKU Data'!D2*'SKU Data'!F2 -> 77490 | E2: =RANK(D2,$D$2:$D$21,0) -> 1 | F2: =SUMPRODUCT(($D$2:$D$21>=D2)*$D$2:$D$21) -> 77490 | G2: =F2/SUM($D$2:$D$21) -> 0.27975032 | H2: =IF(G2<=Assumptions!$B$4,"A",IF(G2<=Assumptions!$B$5,"B","C")) -> A
A3: ='SKU Data'!A3 -> FTW-201 | B3: ='SKU Data'!B3 -> Running Sneakers | C3: ='SKU Data'!C3 -> Footwear | D3: ='SKU Data'!D3*'SKU Data'!F3 -> 31198 | E3: =RANK(D3,$D$2:$D$21,0) -> 2 | F3: =SUMPRODUCT(($D$2:$D$21>=D3)*$D$2:$D$21) -> 108688 | G3: =F3/SUM($D$2:$D$21) -> 0.3923797 | H3: =IF(G3<=Assumptions!$B$4,"A",IF(G3<=Assumptions!$B$5,"B","C")) -> A
A4: ='SKU Data'!A4 -> ACC-302 | B4: ='SKU Data'!B4 -> Aviator Sunglasses | C4: ='SKU Data'!C4 -> Accessories | D4: ='SKU Data'!D4*'SKU Data'!F4 -> 22995 | E4: =RANK(D4,$D$2:$D$21,0) -> 3 | F4: =SUMPRODUCT(($D$2:$D$21>=D4)*$D$2:$D$21) -> 131683 | G4: =F4/SUM($D$2:$D$21) -> 0.47539504 | H4: =IF(G4<=Assumptions!$B$4,"A",IF(G4<=Assumptions!$B$5,"B","C")) -> A
A5: ='SKU Data'!A5 -> FTW-202 | B5: ='SKU Data'!B5 -> Canvas Low-Top | C5: ='SKU Data'!C5 -> Footwear | D5: ='SKU Data'!D5*'SKU Data'!F5 -> 20878 | E5: =RANK(D5,$D$2:$D$21,0) -> 4 | F5: =SUMPRODUCT(($D$2:$D$21>=D5)*$D$2:$D$21) -> 152561 | G5: =F5/SUM($D$2:$D$21) -> 0.5507677 | H5: =IF(G5<=Assumptions!$B$4,"A",IF(G5<=Assumptions!$B$5,"B","C")) -> A
A6: ='SKU Data'!A6 -> ELE-401 | B6: ='SKU Data'!B6 -> Wireless Earbuds | C6: ='SKU Data'!C6 -> Electronics | D6: ='SKU Data'!D6*'SKU Data'!F6 -> 19550 | E6: =RANK(D6,$D$2:$D$21,0) -> 5 | F6: =SUMPRODUCT(($D$2:$D$21>=D6)*$D$2:$D$21) -> 172111 | G6: =F6/SUM($D$2:$D$21) -> 0.62134608 | H6: =IF(G6<=Assumptions!$B$4,"A",IF(G6<=Assumptions!$B$5,"B","C")) -> A
A7: ='SKU Data'!A7 -> FTW-203 | B7: ='SKU Data'!B7 -> Leather Ankle Boot | C7: ='SKU Data'!C7 -> Footwear | D7: ='SKU Data'!D7*'SKU Data'!F7 -> 16276 | E7: =RANK(D7,$D$2:$D$21,0) -> 6 | F7: =SUMPRODUCT(($D$2:$D$21>=D7)*$D$2:$D$21) -> 188387 | G7: =F7/SUM($D$2:$D$21) -> 0.68010484 | H7: =IF(G7<=Assumptions!$B$4,"A",IF(G7<=Assumptions!$B$5,"B","C")) -> A
A8: ='SKU Data'!A8 -> HOM-503 | B8: ='SKU Data'!B8 -> Cotton Throw Blanket | C8: ='SKU Data'!C8 -> Home Goods | D8: ='SKU Data'!D8*'SKU Data'!F8 -> 15360 | E8: =RANK(D8,$D$2:$D$21,0) -> 7 | F8: =SUMPRODUCT(($D$2:$D$21>=D8)*$D$2:$D$21) -> 203747 | G8: =F8/SUM($D$2:$D$21) -> 0.7355567 | H8: =IF(G8<=Assumptions!$B$4,"A",IF(G8<=Assumptions!$B$5,"B","C")) -> A
A9: ='SKU Data'!A9 -> ELE-402 | B9: ='SKU Data'!B9 -> Bluetooth Speaker | C9: ='SKU Data'!C9 -> Electronics | D9: ='SKU Data'!D9*'SKU Data'!F9 -> 13704 | E9: =RANK(D9,$D$2:$D$21,0) -> 8 | F9: =SUMPRODUCT(($D$2:$D$21>=D9)*$D$2:$D$21) -> 217451 | G9: =F9/SUM($D$2:$D$21) -> 0.78503016 | H9: =IF(G9<=Assumptions!$B$4,"A",IF(G9<=Assumptions!$B$5,"B","C")) -> A
A10: ='SKU Data'!A10 -> APP-101 | B10: ='SKU Data'!B10 -> Classic Denim Jacket | C10: ='SKU Data'!C10 -> Apparel | D10: ='SKU Data'!D10*'SKU Data'!F10 -> 9185 | E10: =RANK(D10,$D$2:$D$21,0) -> 9 | F10: =SUMPRODUCT(($D$2:$D$21>=D10)*$D$2:$D$21) -> 226636 | G10: =F10/SUM($D$2:$D$21) -> 0.81818937 | H10: =IF(G10<=Assumptions!$B$4,"A",IF(G10<=Assumptions!$B$5,"B","C")) -> B
A11: ='SKU Data'!A11 -> APP-103 | B11: ='SKU Data'!B11 -> Fleece Pullover Hoodie | C11: ='SKU Data'!C11 -> Apparel | D11: ='SKU Data'!D11*'SKU Data'!F11 -> 7668 | E11: =RANK(D11,$D$2:$D$21,0) -> 10 | F11: =SUMPRODUCT(($D$2:$D$21>=D11)*$D$2:$D$21) -> 241972 | G11: =F11/SUM($D$2:$D$21) -> 0.87355459 | H11: =IF(G11<=Assumptions!$B$4,"A",IF(G11<=Assumptions!$B$5,"B","C")) -> B
A12: ='SKU Data'!A12 -> FTW-204 | B12: ='SKU Data'!B12 -> Slide Sandals | C12: ='SKU Data'!C12 -> Footwear | D12: ='SKU Data'!D12*'SKU Data'!F12 -> 7668 | E12: =RANK(D12,$D$2:$D$21,0) -> 10 | F12: =SUMPRODUCT(($D$2:$D$21>=D12)*$D$2:$D$21) -> 241972 | G12: =F12/SUM($D$2:$D$21) -> 0.87355459 | H12: =IF(G12<=Assumptions!$B$4,"A",IF(G12<=Assumptions!$B$5,"B","C")) -> B
A13: ='SKU Data'!A13 -> HOM-504 | B13: ='SKU Data'!B13 -> Bamboo Cutting Board | C13: ='SKU Data'!C13 -> Home Goods | D13: ='SKU Data'!D13*'SKU Data'!F13 -> 7520 | E13: =RANK(D13,$D$2:$D$21,0) -> 12 | F13: =SUMPRODUCT(($D$2:$D$21>=D13)*$D$2:$D$21) -> 249492 | G13: =F13/SUM($D$2:$D$21) -> 0.9007029 | H13: =IF(G13<=Assumptions!$B$4,"A",IF(G13<=Assumptions!$B$5,"B","C")) -> B
... A21: ='SKU Data'!A21 -> APP-102 | B21: ='SKU Data'!B21 -> Cotton Crew T-Shirt | C21: ='SKU Data'!C21 -> Apparel | D21: ='SKU Data'!D21*'SKU Data'!F21 -> 1553.5 | E21: =RANK(D21,$D$2:$D$21,0) -> 20 | F21: =SUMPRODUCT(($D$2:$D$21>=D21)*$D$2:$D$21) -> 276997 | G21: =F21/SUM($D$2:$D$21) -> 1 | H21: =IF(G21<=Assumptions!$B$4,"A",IF(G21<=Assumptions!$B$5,"B","C")) -> C
A24: ABC Summary
A25: Class | B25: SKU Count | C25: Annual Usage Value | D25: Value Share
A26: A | B26: =COUNTIF($H$2:$H$21, A26) -> 8 | C26: =SUMIF($H$2:$H$21, A26,$D$2:$D$21) -> 217451 | D26: =C26/SUM($D$2:$D$21) -> 0.78503016
A27: B | B27: =COUNTIF($H$2:$H$21, A27) -> 6 | C27: =SUMIF($H$2:$H$21, A27,$D$2:$D$21) -> 43744 | D27: =C27/SUM($D$2:$D$21) -> 0.15792229
A28: C | B28: =COUNTIF($H$2:$H$21, A28) -> 6 | C28: =SUMIF($H$2:$H$21, A28,$D$2:$D$21) -> 15802 | D28: =C28/SUM($D$2:$D$21) -> 0.057047549
A30: ABC Validation
A31: SKU Count Check | B31: =SUM(B26:B28)=COUNTA(A2:A21) -> TRUE
A32: Value Share Check | B32: =ROUND(SUM(D26:D28),4)=1 -> TRUE

Sheet XYZ Analysis
A1: SKU | B1: Product | C1: Category | D1: Avg Daily Demand | E1: Demand Std Dev | F1: Coefficient of Variation | G1: XYZ Class
A2: ='SKU Data'!A2 -> ELE-403 | B2: ='SKU Data'!B2 -> Fitness Tracker Band | C2: ='SKU Data'!C2 -> Electronics | D2: ='SKU Data'!G2 -> 5.05 | E2: ='SKU Data'!H2 -> 1.31 | F2: =IFERROR(E2/D2, 0) -> 0.25940594 | G2: =IF(F2<=Assumptions!$B$10, "X", IF(F2<=Assumptions!$B$11, "Y", "Z")) -> X
A3: ='SKU Data'!A3 -> FTW-201 | B3: ='SKU Data'!B3 -> Running Sneakers | C3: ='SKU Data'!C3 -> Footwear | D3: ='SKU Data'!G3 -> 2.25 | E3: ='SKU Data'!H3 -> 0.77 | F3: =IFERROR(E3/D3, 0) -> 0.34222222 | G3: =IF(F3<=Assumptions!$B$10, "X", IF(F3<=Assumptions!$B$11, "Y", "Z")) -> X
A4: ='SKU Data'!A4 -> ACC-302 | B4: ='SKU Data'!B4 -> Aviator Sunglasses | C4: ='SKU Data'!C4 -> Accessories | D4: ='SKU Data'!G4 -> 4.2 | E4: ='SKU Data'!H4 -> 1.43 | F4: =IFERROR(E4/D4, 0) -> 0.34047619 | G4: =IF(F4<=Assumptions!$B$10, "X", IF(F4<=Assumptions!$B$11, "Y", "Z")) -> X
A5: ='SKU Data'!A5 -> FTW-202 | B5: ='SKU Data'!B5 -> Canvas Low-Top | C5: ='SKU Data'!C5 -> Footwear | D5: ='SKU Data'!G5 -> 2.6 | E5: ='SKU Data'!H5 -> 0.73 | F5: =IFERROR(E5/D5, 0) -> 0.28076923 | G5: =IF(F5<=Assumptions!$B$10, "X", IF(F5<=Assumptions!$B$11, "Y", "Z")) -> X
A6: ='SKU Data'!A6 -> ELE-401 | B6: ='SKU Data'!B6 -> Wireless Earbuds | C6: ='SKU Data'!C6 -> Electronics | D6: ='SKU Data'!G6 -> 1.58 | E6: ='SKU Data'!H6 -> 0.79 | F6: =IFERROR(E6/D6, 0) -> 0.5 | G6: =IF(F6<=Assumptions!$B$10, "X", IF(F6<=Assumptions!$B$11, "Y", "Z")) -> X
A7: ='SKU Data'!A7 -> FTW-203 | B7: ='SKU Data'!B7 -> Leather Ankle Boot | C7: ='SKU Data'!C7 -> Footwear | D7: ='SKU Data'!G7 -> 0.86 | E7: ='SKU Data'!H7 -> 0.38 | F7: =IFERROR(E7/D7, 0) -> 0.44186047 | G7: =IF(F7<=Assumptions!$B$10, "X", IF(F7<=Assumptions!$B$11, "Y", "Z")) -> X
A8: ='SKU Data'!A8 -> HOM-503 | B8: ='SKU Data'!B8 -> Cotton Throw Blanket | C8: ='SKU Data'!C8 -> Home Goods | D8: ='SKU Data'!G8 -> 2.81 | E8: ='SKU Data'!H8 -> 1.52 | F8: =IFERROR(E8/D8, 0) -> 0.54092527 | G8: =IF(F8<=Assumptions!$B$10, "X", IF(F8<=Assumptions!$B$11, "Y", "Z")) -> Y
A9: ='SKU Data'!A9 -> ELE-402 | B9: ='SKU Data'!B9 -> Bluetooth Speaker | C9: ='SKU Data'!C9 -> Electronics | D9: ='SKU Data'!G9 -> 1.56 | E9: ='SKU Data'!H9 -> 0.69 | F9: =IFERROR(E9/D9, 0) -> 0.44230769 | G9: =IF(F9<=Assumptions!$B$10, "X", IF(F9<=Assumptions!$B$11, "Y", "Z")) -> X
A10: ='SKU Data'!A10 -> APP-101 | B10: ='SKU Data'!B10 -> Classic Denim Jacket | C10: ='SKU Data'!C10 -> Apparel | D10: ='SKU Data'!G10 -> 0.92 | E10: ='SKU Data'!H10 -> 0.34 | F10: =IFERROR(E10/D10, 0) -> 0.36956522 | G10: =IF(F10<=Assumptions!$B$10, "X", IF(F10<=Assumptions!$B$11, "Y", "Z")) -> X
A11: ='SKU Data'!A11 -> APP-103 | B11: ='SKU Data'!B11 -> Fleece Pullover Hoodie | C11: ='SKU Data'!C11 -> Apparel | D11: ='SKU Data'!G11 -> 1.17 | E11: ='SKU Data'!H11 -> 0.33 | F11: =IFERROR(E11/D11, 0) -> 0.28205128 | G11: =IF(F11<=Assumptions!$B$10, "X", IF(F11<=Assumptions!$B$11, "Y", "Z")) -> X
A12: ='SKU Data'!A12 -> FTW-204 | B12: ='SKU Data'!B12 -> Slide Sandals | C12: ='SKU Data'!C12 -> Footwear | D12: ='SKU Data'!G12 -> 2.33 | E12: ='SKU Data'!H12 -> 1 | F12: =IFERROR(E12/D12, 0) -> 0.42918455 | G12: =IF(F12<=Assumptions!$B$10, "X", IF(F12<=Assumptions!$B$11, "Y", "Z")) -> X
A13: ='SKU Data'!A13 -> HOM-504 | B13: ='SKU Data'!B13 -> Bamboo Cutting Board | C13: ='SKU Data'!C13 -> Home Goods | D13: ='SKU Data'!G13 -> 2.06 | E13: ='SKU Data'!H13 -> 0.52 | F13: =IFERROR(E13/D13, 0) -> 0.25242718 | G13: =IF(F13<=Assumptions!$B$10, "X", IF(F13<=Assumptions!$B$11, "Y", "Z")) -> X
... A21: ='SKU Data'!A21 -> APP-102 | B21: ='SKU Data'!B21 -> Cotton Crew T-Shirt | C21: ='SKU Data'!C21 -> Apparel | D21: ='SKU Data'!G21 -> 0.65 | E21: ='SKU Data'!H21 -> 0.34 | F21: =IFERROR(E21/D21, 0) -> 0.52307692 | G21: =IF(F21<=Assumptions!$B$10, "X", IF(F21<=Assumptions!$B$11, "Y", "Z")) -> Y
A24: XYZ Summary
A25: Class | B25: SKU Count
A26: X | B26: =COUNTIF($G$2:$G$21,A26) -> 16
A27: Y | B27: =COUNTIF($G$2:$G$21,A27) -> 4
A28: Z | B28: =COUNTIF($G$2:$G$21,A28) -> 0
A29: Total | B29: =SUM(B26:B28) -> 20
A31: XYZ Validation
A32: SKU Count Check | B32: =SUM(B26:B28)=COUNTA(A2:A21) -> TRUE

Sheet ABC-XYZ Matrix
A1: SKU | B1: Product | C1: ABC Class | D1: XYZ Class | E1: ABC-XYZ Segment
A2: ='SKU Data'!A2 -> ELE-403 | B2: =SKUData[[#This Row],[Product]] -> Fitness Tracker Band | C2: =INDEX('ABC Analysis'!$H$2:$H$21,MATCH(A2,'ABC Analysis'!$A$2:$A$21,0)) -> A | D2: =INDEX('XYZ Analysis'!$G$2:$G$21,MATCH(A2,'XYZ Analysis'!$A$2:$A$21,0)) -> X | E2: =C2&D2 -> AX
A3: ='SKU Data'!A3 -> FTW-201 | B3: =SKUData[[#This Row],[Product]] -> Running Sneakers | C3: =INDEX('ABC Analysis'!$H$2:$H$21,MATCH(A3,'ABC Analysis'!$A$2:$A$21,0)) -> A | D3: =INDEX('XYZ Analysis'!$G$2:$G$21,MATCH(A3,'XYZ Analysis'!$A$2:$A$21,0)) -> X | E3: =C3&D3 -> AX
A4: ='SKU Data'!A4 -> ACC-302 | B4: =SKUData[[#This Row],[Product]] -> Aviator Sunglasses | C4: =INDEX('ABC Analysis'!$H$2:$H$21,MATCH(A4,'ABC Analysis'!$A$2:$A$21,0)) -> A | D4: =INDEX('XYZ Analysis'!$G$2:$G$21,MATCH(A4,'XYZ Analysis'!$A$2:$A$21,0)) -> X | E4: =C4&D4 -> AX
A5: ='SKU Data'!A5 -> FTW-202 | B5: =SKUData[[#This Row],[Product]] -> Canvas Low-Top | C5: =INDEX('ABC Analysis'!$H$2:$H$21,MATCH(A5,'ABC Analysis'!$A$2:$A$21,0)) -> A | D5: =INDEX('XYZ Analysis'!$G$2:$G$21,MATCH(A5,'XYZ Analysis'!$A$2:$A$21,0)) -> X | E5: =C5&D5 -> AX
A6: ='SKU Data'!A6 -> ELE-401 | B6: =SKUData[[#This Row],[Product]] -> Wireless Earbuds | C6: =INDEX('ABC Analysis'!$H$2:$H$21,MATCH(A6,'ABC Analysis'!$A$2:$A$21,0)) -> A | D6: =INDEX('XYZ Analysis'!$G$2:$G$21,MATCH(A6,'XYZ Analysis'!$A$2:$A$21,0)) -> X | E6: =C6&D6 -> AX
A7: ='SKU Data'!A7 -> FTW-203 | B7: =SKUData[[#This Row],[Product]] -> Leather Ankle Boot | C7: =INDEX('ABC Analysis'!$H$2:$H$21,MATCH(A7,'ABC Analysis'!$A$2:$A$21,0)) -> A | D7: =INDEX('XYZ Analysis'!$G$2:$G$21,MATCH(A7,'XYZ Analysis'!$A$2:$A$21,0)) -> X | E7: =C7&D7 -> AX
A8: ='SKU Data'!A8 -> HOM-503 | B8: =SKUData[[#This Row],[Product]] -> Cotton Throw Blanket | C8: =INDEX('ABC Analysis'!$H$2:$H$21,MATCH(A8,'ABC Analysis'!$A$2:$A$21,0)) -> A | D8: =INDEX('XYZ Analysis'!$G$2:$G$21,MATCH(A8,'XYZ Analysis'!$A$2:$A$21,0)) -> Y | E8: =C8&D8 -> AY
A9: ='SKU Data'!A9 -> ELE-402 | B9: =SKUData[[#This Row],[Product]] -> Bluetooth Speaker | C9: =INDEX('ABC Analysis'!$H$2:$H$21,MATCH(A9,'ABC Analysis'!$A$2:$A$21,0)) -> A | D9: =INDEX('XYZ Analysis'!$G$2:$G$21,MATCH(A9,'XYZ Analysis'!$A$2:$A$21,0)) -> X | E9: =C9&D9 -> AX
A10: ='SKU Data'!A10 -> APP-101 | B10: =SKUData[[#This Row],[Product]] -> Classic Denim Jacket | C10: =INDEX('ABC Analysis'!$H$2:$H$21,MATCH(A10,'ABC Analysis'!$A$2:$A$21,0)) -> B | D10: =INDEX('XYZ Analysis'!$G$2:$G$21,MATCH(A10,'XYZ Analysis'!$A$2:$A$21,0)) -> X | E10: =C10&D10 -> BX
A11: ='SKU Data'!A11 -> APP-103 | B11: =SKUData[[#This Row],[Product]] -> Fleece Pullover Hoodie | C11: =INDEX('ABC Analysis'!$H$2:$H$21,MATCH(A11,'ABC Analysis'!$A$2:$A$21,0)) -> B | D11: =INDEX('XYZ Analysis'!$G$2:$G$21,MATCH(A11,'XYZ Analysis'!$A$2:$A$21,0)) -> X | E11: =C11&D11 -> BX
A12: ='SKU Data'!A12 -> FTW-204 | B12: =SKUData[[#This Row],[Product]] -> Slide Sandals | C12: =INDEX('ABC Analysis'!$H$2:$H$21,MATCH(A12,'ABC Analysis'!$A$2:$A$21,0)) -> B | D12: =INDEX('XYZ Analysis'!$G$2:$G$21,MATCH(A12,'XYZ Analysis'!$A$2:$A$21,0)) -> X | E12: =C12&D12 -> BX
A13: ='SKU Data'!A13 -> HOM-504 | B13: =SKUData[[#This Row],[Product]] -> Bamboo Cutting Board | C13: =INDEX('ABC Analysis'!$H$2:$H$21,MATCH(A13,'ABC Analysis'!$A$2:$A$21,0)) -> B | D13: =INDEX('XYZ Analysis'!$G$2:$G$21,MATCH(A13,'XYZ Analysis'!$A$2:$A$21,0)) -> X | E13: =C13&D13 -> BX
... A21: ='SKU Data'!A21 -> APP-102 | B21: =SKUData[[#This Row],[Product]] -> Cotton Crew T-Shirt | C21: =INDEX('ABC Analysis'!$H$2:$H$21,MATCH(A21,'ABC Analysis'!$A$2:$A$21,0)) -> C | D21: =INDEX('XYZ Analysis'!$G$2:$G$21,MATCH(A21,'XYZ Analysis'!$A$2:$A$21,0)) -> Y | E21: =C21&D21 -> CY
A24: ABC-XYZ Matrix
A25: ABC / XYZ | B25: X | C25: Y | D25: Z
A26: A | B26: =COUNTIFS($C$2:$C$21, $A26, $D$2:$D$21, B$25) -> 7 | C26: =COUNTIFS($C$2:$C$21, $A26, $D$2:$D$21, C$25) -> 1 | D26: =COUNTIFS($C$2:$C$21, $A26, $D$2:$D$21, D$25) -> 0
A27: B | B27: =COUNTIFS($C$2:$C$21, $A27, $D$2:$D$21, B$25) -> 6 | C27: =COUNTIFS($C$2:$C$21, $A27, $D$2:$D$21, C$25) -> 0 | D27: =COUNTIFS($C$2:$C$21, $A27, $D$2:$D$21, D$25) -> 0
A28: C | B28: =COUNTIFS($C$2:$C$21, $A28, $D$2:$D$21, B$25) -> 3 | C28: =COUNTIFS($C$2:$C$21, $A28, $D$2:$D$21, C$25) -> 3 | D28: =COUNTIFS($C$2:$C$21, $A28, $D$2:$D$21, D$25) -> 0
A29: Total | B29: =SUM(B26:D28) -> 20
A31: ABC-XYZ Validation
A32: SKU Count Check | B32: =B29=COUNTA(A2:A21) -> TRUE

Sheet Reorder Point Model
A1: SKU | B1: Product | C1: Class | D1: Avg Daily Demand | E1: Demand Std Dev | F1: Lead Time (days) | G1: Service Level Z | H1: Safety Stock | I1: Reorder Point | J1: EOQ | K1: Annual Orders (EOQ) | M1: Service Level by Class (Z-score)
A2: ='SKU Data'!A2 -> ELE-403 | B2: ='SKU Data'!B2 -> Fitness Tracker Band | C2: =INDEX('ABC Analysis'!$H$2:$H$21,MATCH(A2,'ABC Analysis'!$A$2:$A$21,0)) -> A | D2: ='SKU Data'!G2 -> 5.05 | E2: ='SKU Data'!H2 -> 1.31 | F2: ='SKU Data'!I2 -> 45 | G2: =INDEX($N$2:$N$4,MATCH(C2,$M$2:$M$4,0)) -> 2.33 | H2: =G2*E2*SQRT(F2) -> 20.475451 | I2: =(D2*F2)+H2 -> 247.72545 | J2: =SQRT((2*'SKU Data'!F2*'SKU Data'!J2)/('SKU Data'!D2*'SKU Data'!K2)) -> 173.82525 | K2: =IFERROR('SKU Data'!F2/J2,0) -> 10.614108 | M2: A | N2: 2.33 | O2: ~99% service level
A3: ='SKU Data'!A3 -> FTW-201 | B3: ='SKU Data'!B3 -> Running Sneakers | C3: =INDEX('ABC Analysis'!$H$2:$H$21,MATCH(A3,'ABC Analysis'!$A$2:$A$21,0)) -> A | D3: ='SKU Data'!G3 -> 2.25 | E3: ='SKU Data'!H3 -> 0.77 | F3: ='SKU Data'!I3 -> 14 | G3: =INDEX($N$2:$N$4,MATCH(C3,$M$2:$M$4,0)) -> 2.33 | H3: =G3*E3*SQRT(F3) -> 6.7129075 | I3: =(D3*F3)+H3 -> 38.212908 | J3: =SQRT((2*'SKU Data'!F3*'SKU Data'!J3)/('SKU Data'!D3*'SKU Data'!K3)) -> 139.78202 | K3: =IFERROR('SKU Data'!F3/J3,0) -> 5.8734305 | M3: B | N3: 1.65 | O3: ~95% service level
A4: ='SKU Data'!A4 -> ACC-302 | B4: ='SKU Data'!B4 -> Aviator Sunglasses | C4: =INDEX('ABC Analysis'!$H$2:$H$21,MATCH(A4,'ABC Analysis'!$A$2:$A$21,0)) -> A | D4: ='SKU Data'!G4 -> 4.2 | E4: ='SKU Data'!H4 -> 1.43 | F4: ='SKU Data'!I4 -> 10 | G4: =INDEX($N$2:$N$4,MATCH(C4,$M$2:$M$4,0)) -> 2.33 | H4: =G4*E4*SQRT(F4) -> 10.536393 | I4: =(D4*F4)+H4 -> 52.536393 | J4: =SQRT((2*'SKU Data'!F4*'SKU Data'!J4)/('SKU Data'!D4*'SKU Data'!K4)) -> 232.71394 | K4: =IFERROR('SKU Data'!F4/J4,0) -> 6.5874866 | M4: C | N4: 1.28 | O4: ~90% service level
A5: ='SKU Data'!A5 -> FTW-202 | B5: ='SKU Data'!B5 -> Canvas Low-Top | C5: =INDEX('ABC Analysis'!$H$2:$H$21,MATCH(A5,'ABC Analysis'!$A$2:$A$21,0)) -> A | D5: ='SKU Data'!G5 -> 2.6 | E5: ='SKU Data'!H5 -> 0.73 | F5: ='SKU Data'!I5 -> 14 | G5: =INDEX($N$2:$N$4,MATCH(C5,$M$2:$M$4,0)) -> 2.33 | H5: =G5*E5*SQRT(F5) -> 6.364185 | I5: =(D5*F5)+H5 -> 42.764185 | J5: =SQRT((2*'SKU Data'!F5*'SKU Data'!J5)/('SKU Data'!D5*'SKU Data'!K5)) -> 178.18071 | K5: =IFERROR('SKU Data'!F5/J5,0) -> 5.3260537
A6: ='SKU Data'!A6 -> ELE-401 | B6: ='SKU Data'!B6 -> Wireless Earbuds | C6: =INDEX('ABC Analysis'!$H$2:$H$21,MATCH(A6,'ABC Analysis'!$A$2:$A$21,0)) -> A | D6: ='SKU Data'!G6 -> 1.58 | E6: ='SKU Data'!H6 -> 0.79 | F6: ='SKU Data'!I6 -> 21 | G6: =INDEX($N$2:$N$4,MATCH(C6,$M$2:$M$4,0)) -> 2.33 | H6: =G6*E6*SQRT(F6) -> 8.4351471 | I6: =(D6*F6)+H6 -> 41.615147 | J6: =SQRT((2*'SKU Data'!F6*'SKU Data'!J6)/('SKU Data'!D6*'SKU Data'!K6)) -> 113.95976 | K6: =IFERROR('SKU Data'!F6/J6,0) -> 5.0456409
A7: ='SKU Data'!A7 -> FTW-203 | B7: ='SKU Data'!B7 -> Leather Ankle Boot | C7: =INDEX('ABC Analysis'!$H$2:$H$21,MATCH(A7,'ABC Analysis'!$A$2:$A$21,0)) -> A | D7: ='SKU Data'!G7 -> 0.86 | E7: ='SKU Data'!H7 -> 0.38 | F7: ='SKU Data'!I7 -> 45 | G7: =INDEX($N$2:$N$4,MATCH(C7,$M$2:$M$4,0)) -> 2.33 | H7: =G7*E7*SQRT(F7) -> 5.9394438 | I7: =(D7*F7)+H7 -> 44.639444 | J7: =SQRT((2*'SKU Data'!F7*'SKU Data'!J7)/('SKU Data'!D7*'SKU Data'!K7)) -> 81.137653 | K7: =IFERROR('SKU Data'!F7/J7,0) -> 3.8576418
A8: ='SKU Data'!A8 -> HOM-503 | B8: ='SKU Data'!B8 -> Cotton Throw Blanket | C8: =INDEX('ABC Analysis'!$H$2:$H$21,MATCH(A8,'ABC Analysis'!$A$2:$A$21,0)) -> A | D8: ='SKU Data'!G8 -> 2.81 | E8: ='SKU Data'!H8 -> 1.52 | F8: ='SKU Data'!I8 -> 14 | G8: =INDEX($N$2:$N$4,MATCH(C8,$M$2:$M$4,0)) -> 2.33 | H8: =G8*E8*SQRT(F8) -> 13.251454 | I8: =(D8*F8)+H8 -> 52.591454 | J8: =SQRT((2*'SKU Data'!F8*'SKU Data'!J8)/('SKU Data'!D8*'SKU Data'!K8)) -> 198.64071 | K8: =IFERROR('SKU Data'!F8/J8,0) -> 5.1550358
A9: ='SKU Data'!A9 -> ELE-402 | B9: ='SKU Data'!B9 -> Bluetooth Speaker | C9: =INDEX('ABC Analysis'!$H$2:$H$21,MATCH(A9,'ABC Analysis'!$A$2:$A$21,0)) -> A | D9: ='SKU Data'!G9 -> 1.56 | E9: ='SKU Data'!H9 -> 0.69 | F9: ='SKU Data'!I9 -> 45 | G9: =INDEX($N$2:$N$4,MATCH(C9,$M$2:$M$4,0)) -> 2.33 | H9: =G9*E9*SQRT(F9) -> 10.784779 | I9: =(D9*F9)+H9 -> 80.984779 | J9: =SQRT((2*'SKU Data'!F9*'SKU Data'!J9)/('SKU Data'!D9*'SKU Data'!K9)) -> 130.25298 | K9: =IFERROR('SKU Data'!F9/J9,0) -> 4.383777
A10: ='SKU Data'!A10 -> APP-101 | B10: ='SKU Data'!B10 -> Classic Denim Jacket | C10: =INDEX('ABC Analysis'!$H$2:$H$21,MATCH(A10,'ABC Analysis'!$A$2:$A$21,0)) -> B | D10: ='SKU Data'!G10 -> 0.92 | E10: ='SKU Data'!H10 -> 0.34 | F10: ='SKU Data'!I10 -> 7 | G10: =INDEX($N$2:$N$4,MATCH(C10,$M$2:$M$4,0)) -> 1.65 | H10: =G10*E10*SQRT(F10) -> 1.4842665 | I10: =(D10*F10)+H10 -> 7.9242665 | J10: =SQRT((2*'SKU Data'!F10*'SKU Data'!J10)/('SKU Data'!D10*'SKU Data'!K10)) -> 72.77721 | K10: =IFERROR('SKU Data'!F10/J10,0) -> 4.5893488
A11: ='SKU Data'!A11 -> APP-103 | B11: ='SKU Data'!B11 -> Fleece Pullover Hoodie | C11: =INDEX('ABC Analysis'!$H$2:$H$21,MATCH(A11,'ABC Analysis'!$A$2:$A$21,0)) -> B | D11: ='SKU Data'!G11 -> 1.17 | E11: ='SKU Data'!H11 -> 0.33 | F11: ='SKU Data'!I11 -> 30 | G11: =INDEX($N$2:$N$4,MATCH(C11,$M$2:$M$4,0)) -> 1.65 | H11: =G11*E11*SQRT(F11) -> 2.9823493 | I11: =(D11*F11)+H11 -> 38.082349 | J11: =SQRT((2*'SKU Data'!F11*'SKU Data'!J11)/('SKU Data'!D11*'SKU Data'!K11)) -> 100.02272 | K11: =IFERROR('SKU Data'!F11/J11,0) -> 4.2590321
A12: ='SKU Data'!A12 -> FTW-204 | B12: ='SKU Data'!B12 -> Slide Sandals | C12: =INDEX('ABC Analysis'!$H$2:$H$21,MATCH(A12,'ABC Analysis'!$A$2:$A$21,0)) -> B | D12: ='SKU Data'!G12 -> 2.33 | E12: ='SKU Data'!H12 -> 1 | F12: ='SKU Data'!I12 -> 45 | G12: =INDEX($N$2:$N$4,MATCH(C12,$M$2:$M$4,0)) -> 1.65 | H12: =G12*E12*SQRT(F12) -> 11.068536 | I12: =(D12*F12)+H12 -> 115.91854 | J12: =SQRT((2*'SKU Data'!F12*'SKU Data'!J12)/('SKU Data'!D12*'SKU Data'!K12)) -> 289.66571 | K12: =IFERROR('SKU Data'!F12/J12,0) -> 2.9413216
A13: ='SKU Data'!A13 -> HOM-504 | B13: ='SKU Data'!B13 -> Bamboo Cutting Board | C13: =INDEX('ABC Analysis'!$H$2:$H$21,MATCH(A13,'ABC Analysis'!$A$2:$A$21,0)) -> B | D13: ='SKU Data'!G13 -> 2.06 | E13: ='SKU Data'!H13 -> 0.52 | F13: ='SKU Data'!I13 -> 14 | G13: =INDEX($N$2:$N$4,MATCH(C13,$M$2:$M$4,0)) -> 1.65 | H13: =G13*E13*SQRT(F13) -> 3.210342 | I13: =(D13*F13)+H13 -> 32.050342 | J13: =SQRT((2*'SKU Data'!F13*'SKU Data'!J13)/('SKU Data'!D13*'SKU Data'!K13)) -> 262.83785 | K13: =IFERROR('SKU Data'!F13/J13,0) -> 2.8610796
A14: ='SKU Data'!A14 -> HOM-501 | B14: ='SKU Data'!B14 -> Ceramic Coffee Mug Set | C14: =INDEX('ABC Analysis'!$H$2:$H$21,MATCH(A14,'ABC Analysis'!$A$2:$A$21,0)) -> B | D14: ='SKU Data'!G14 -> 2.26 | E14: ='SKU Data'!H14 -> 0.61 | F14: ='SKU Data'!I14 -> 45 | G14: =INDEX($N$2:$N$4,MATCH(C14,$M$2:$M$4,0)) -> 1.65 | H14: =G14*E14*SQRT(F14) -> 6.7518073 | I14: =(D14*F14)+H14 -> 108.45181 | J14: =SQRT((2*'SKU Data'!F14*'SKU Data'!J14)/('SKU Data'!D14*'SKU Data'!K14)) -> 302.2906 | K14: =IFERROR('SKU Data'!F14/J14,0) -> 2.729162
A15: ='SKU Data'!A15 -> APP-104 | B15: ='SKU Data'!B15 -> Slim Fit Chinos | C15: =INDEX('ABC Analysis'!$H$2:$H$21,MATCH(A15,'ABC Analysis'!$A$2:$A$21,0)) -> B | D15: ='SKU Data'!G15 -> 0.67 | E15: ='SKU Data'!H15 -> 0.28 | F15: ='SKU Data'!I15 -> 30 | G15: =INDEX($N$2:$N$4,MATCH(C15,$M$2:$M$4,0)) -> 1.65 | H15: =G15*E15*SQRT(F15) -> 2.5304782 | I15: =(D15*F15)+H15 -> 22.630478 | J15: =SQRT((2*'SKU Data'!F15*'SKU Data'!J15)/('SKU Data'!D15*'SKU Data'!K15)) -> 76.443256 | K15: =IFERROR('SKU Data'!F15/J15,0) -> 3.1788285
A16: ='SKU Data'!A16 -> ACC-304 | B16: ='SKU Data'!B16 -> Wool Beanie | C16: =INDEX('ABC Analysis'!$H$2:$H$21,MATCH(A16,'ABC Analysis'!$A$2:$A$21,0)) -> C | D16: ='SKU Data'!G16 -> 2.19 | E16: ='SKU Data'!H16 -> 0.77 | F16: ='SKU Data'!I16 -> 21 | G16: =INDEX($N$2:$N$4,MATCH(C16,$M$2:$M$4,0)) -> 1.28 | H16: =G16*E16*SQRT(F16) -> 4.5165866 | I16: =(D16*F16)+H16 -> 50.506587 | J16: =SQRT((2*'SKU Data'!F16*'SKU Data'!J16)/('SKU Data'!D16*'SKU Data'!K16)) -> 365.31297 | K16: =IFERROR('SKU Data'!F16/J16,0) -> 2.1926405
... A21: ='SKU Data'!A21 -> APP-102 | B21: ='SKU Data'!B21 -> Cotton Crew T-Shirt | C21: =INDEX('ABC Analysis'!$H$2:$H$21,MATCH(A21,'ABC Analysis'!$A$2:$A$21,0)) -> C | D21: ='SKU Data'!G21 -> 0.65 | E21: ='SKU Data'!H21 -> 0.34 | F21: ='SKU Data'!I21 -> 14 | G21: =INDEX($N$2:$N$4,MATCH(C21,$M$2:$M$4,0)) -> 1.28 | H21: =G21*E21*SQRT(F21) -> 1.6283693 | I21: =(D21*F21)+H21 -> 10.728369 | J21: =SQRT((2*'SKU Data'!F21*'SKU Data'!J21)/('SKU Data'!D21*'SKU Data'!K21)) -> 124.29835 | K21: =IFERROR('SKU Data'!F21/J21,0) -> 1.922793
